{
  "name": "withDefs",
  "defs": [
    {
      "kind": "var",
      "name": "n",
      "type": {
        "kind": "int"
      }
    },
    {
      "kind": "def",
      "name": "G",
      "qualifier": "def",
      "expr": {
        "kind": "lambda",
        "params": ["x", "y"],
        "qualifier": "def",
        "expr": {
          "kind": "app",
          "opcode": "iadd",
          "args": [
            { "kind": "name", "name": "x" },
            { "kind": "name", "name": "y" }
          ]
        }
      }
    },
    {
      "kind": "def",
      "name": "P",
      "qualifier": "pred",
      "expr": {
        "kind": "lambda",
        "params": ["x", "y"],
        "qualifier": "pred",
        "expr": {
          "kind": "app",
          "opcode": "igt",
          "args": [
            { "kind": "name", "name": "x" },
            { "kind": "name", "name": "y" }
          ]
        }
      }
    },
    {
      "kind": "def",
      "name": "A",
      "qualifier": "action",
      "expr": {
        "kind": "lambda",
        "params": ["x"],
        "qualifier": "action",
        "expr": {
          "kind": "app",
          "opcode": "assign",
          "args": [
            { "kind": "name", "name": "n" },
            { "kind": "name", "name": "x" }
          ]
        }
      }
    },
    {
      "kind": "def",
      "name": "F",
      "qualifier": "temporal",
      "expr": {
        "kind": "lambda",
        "params": ["x"],
        "qualifier": "temporal",
        "expr": {
          "kind": "app",
          "opcode": "not",
          "args": [
            { "kind": "name", "name": "x" }
          ]
        }
      }
    }
  ]
}
