{
  "1": {
    "source": "mocked_path/testFixture/_0119expr_block_and.tnt",
    "start": {
      "line": 5,
      "col": 4,
      "index": 224
    },
    "end": {
      "line": 5,
      "col": 4,
      "index": 228
    }
  },
  "2": {
    "source": "mocked_path/testFixture/_0119expr_block_and.tnt",
    "start": {
      "line": 6,
      "col": 4,
      "index": 234
    },
    "end": {
      "line": 6,
      "col": 4,
      "index": 237
    }
  },
  "3": {
    "source": "mocked_path/testFixture/_0119expr_block_and.tnt",
    "start": {
      "line": 7,
      "col": 4,
      "index": 243
    },
    "end": {
      "line": 7,
      "col": 4,
      "index": 247
    }
  },
  "4": {
    "source": "mocked_path/testFixture/_0119expr_block_and.tnt",
    "start": {
      "line": 4,
      "col": 22,
      "index": 218
    },
    "end": {
      "line": 8,
      "col": 1,
      "index": 250
    }
  },
  "5": {
    "source": "mocked_path/testFixture/_0119expr_block_and.tnt",
    "start": {
      "line": 4,
      "col": 1,
      "index": 197
    },
    "end": {
      "line": 8,
      "col": 1,
      "index": 250
    }
  },
  "7": {
    "source": "mocked_path/testFixture/_0119expr_block_and.tnt",
    "start": {
      "line": 3,
      "col": 0,
      "index": 178
    },
    "end": {
      "line": 9,
      "col": 0,
      "index": 252
    }
  }
}
