{"stage":"parsing","warnings":[],"modules":[{"id":3,"name":"M","declarations":[{"id":2,"kind":"def","name":"b","qualifier":"def","expr":{"id":1,"kind":"int","value":2}}]},{"id":21,"name":"conflictingNames","declarations":[{"id":13,"kind":"def","name":"size","qualifier":"def","expr":{"id":12,"kind":"lambda","params":[{"id":10,"name":"x"}],"qualifier":"def","expr":{"id":11,"kind":"int","value":0}}},{"id":15,"kind":"typedef","name":"T","type":{"id":14,"kind":"int"},"depth":0},{"id":17,"kind":"typedef","name":"T","type":{"id":16,"kind":"str"},"depth":0},{"id":19,"kind":"def","name":"b","qualifier":"def","expr":{"id":18,"kind":"int","value":1}},{"kind":"var","name":"a","typeAnnotation":{"id":4,"kind":"int"},"id":5,"depth":0},{"id":20,"kind":"import","defName":"b","protoName":"M"},{"id":9,"kind":"def","name":"a","qualifier":"def","expr":{"id":8,"kind":"lambda","params":[{"id":6,"name":"x"}],"qualifier":"def","expr":{"id":7,"kind":"name","name":"x"}}}]}],"table":{"2":{"id":2,"kind":"def","name":"b","qualifier":"def","expr":{"id":1,"kind":"int","value":2},"depth":0},"7":{"id":6,"name":"x","kind":"param","depth":1},"9":{"id":9,"kind":"def","name":"a","qualifier":"def","expr":{"id":8,"kind":"lambda","params":[{"id":6,"name":"x"}],"qualifier":"def","expr":{"id":7,"kind":"name","name":"x"}},"depth":0},"13":{"id":13,"kind":"def","name":"size","qualifier":"def","expr":{"id":12,"kind":"lambda","params":[{"id":10,"name":"x"}],"qualifier":"def","expr":{"id":11,"kind":"int","value":0}},"depth":0},"19":{"id":19,"kind":"def","name":"b","qualifier":"def","expr":{"id":18,"kind":"int","value":1},"depth":0}},"errors":[{"explanation":"[QNT101] Conflicting definitions found for name 'a' in module 'conflictingNames'","locs":[{"source":"mocked_path/testFixture/_1014conflictingNames.qnt","start":{"line":6,"col":2,"index":73},"end":{"line":6,"col":12,"index":83}}]},{"explanation":"[QNT101] Conflicting definitions found for name 'a' in module 'conflictingNames'","locs":[{"source":"mocked_path/testFixture/_1014conflictingNames.qnt","start":{"line":7,"col":6,"index":91},"end":{"line":7,"col":6,"index":91}}]},{"explanation":"[QNT101] Built-in name 'size' is redefined in module 'conflictingNames'","locs":[{"source":"mocked_path/testFixture/_1014conflictingNames.qnt","start":{"line":10,"col":6,"index":146},"end":{"line":10,"col":9,"index":149}}]},{"explanation":"[QNT101] Conflicting definitions found for name 'T' in module 'conflictingNames'","locs":[{"source":"mocked_path/testFixture/_1014conflictingNames.qnt","start":{"line":13,"col":2,"index":186},"end":{"line":13,"col":13,"index":197}}]},{"explanation":"[QNT101] Conflicting definitions found for name 'T' in module 'conflictingNames'","locs":[{"source":"mocked_path/testFixture/_1014conflictingNames.qnt","start":{"line":14,"col":2,"index":201},"end":{"line":14,"col":13,"index":212}}]},{"explanation":"[QNT101] Conflicting definitions found for name 'b' in module 'conflictingNames'","locs":[{"source":"mocked_path/testFixture/_1014conflictingNames.qnt","start":{"line":16,"col":6,"index":221},"end":{"line":16,"col":6,"index":221}}]},{"explanation":"[QNT101] Conflicting definitions found for name 'b' in module 'conflictingNames'","locs":[{"source":"mocked_path/testFixture/_1014conflictingNames.qnt","start":{"line":19,"col":2,"index":271},"end":{"line":19,"col":11,"index":280}}]}]}