{"stage":"parsing","warnings":[],"modules":[{"id":2,"name":"importer","declarations":[{"id":1,"kind":"import","defName":"*","protoName":"boson","fromSource":"./non-existant-file"}]}],"table":{},"errors":[{"explanation":"[QNT013] import ... from './non-existant-file': could not load","locs":[{"source":"mocked_path/testFixture/_1023importFromUnresolved.qnt","start":{"line":1,"col":2,"index":20},"end":{"line":1,"col":42,"index":60}}]},{"explanation":"[QNT405] Module 'boson' not found","locs":[{"source":"mocked_path/testFixture/_1023importFromUnresolved.qnt","start":{"line":1,"col":2,"index":20},"end":{"line":1,"col":42,"index":60}}]}]}