{"sourceIndex":{"0":"mocked_path/testFixture/_1020importFrom.qnt","3":"mocked_path/testFixture/_1022importee2.qnt","6":"mocked_path/testFixture/_1021importee1.qnt"},"map":{"1":[0,{"line":1,"col":2,"index":20},{"line":1,"col":47,"index":65}],"2":[0,{"line":2,"col":2,"index":69},{"line":2,"col":47,"index":114}],"3":[0,{"line":0,"col":0,"index":0},{"line":3,"col":116,"index":116}],"4":[3,{"line":1,"col":14,"index":33},{"line":1,"col":24,"index":43}],"5":[3,{"line":1,"col":2,"index":21},{"line":1,"col":24,"index":43}],"6":[3,{"line":0,"col":0,"index":0},{"line":2,"col":45,"index":45}],"7":[6,{"line":1,"col":14,"index":33},{"line":1,"col":24,"index":43}],"8":[6,{"line":1,"col":2,"index":21},{"line":1,"col":24,"index":43}],"9":[6,{"line":3,"col":2,"index":48},{"line":3,"col":47,"index":93}],"10":[6,{"line":0,"col":0,"index":0},{"line":4,"col":95,"index":95}]}}