{"stage":"parsing","warnings":[],"modules":[{"id":12,"name":"ModuleToImport","declarations":[{"id":11,"kind":"def","name":"step","qualifier":"action","expr":{"id":10,"kind":"bool","value":true}},{"id":7,"kind":"def","name":"importedValue","qualifier":"val","expr":{"id":6,"kind":"int","value":0}},{"id":9,"kind":"def","name":"init","qualifier":"action","expr":{"id":8,"kind":"bool","value":true}}]},{"id":5,"name":"ModuleToInstantiate","declarations":[{"kind":"const","name":"C","typeAnnotation":{"id":1,"kind":"int"},"id":2,"depth":0},{"id":4,"kind":"def","name":"instantiatedValue","qualifier":"val","expr":{"id":3,"kind":"name","name":"C"}}]},{"id":67,"name":"ApalacheCompilation","declarations":[{"kind":"var","name":"x","typeAnnotation":{"id":17,"kind":"int"},"id":18,"depth":0},{"id":21,"kind":"typedef","name":"T","type":{"id":21,"kind":"sum","fields":{"kind":"row","fields":[{"fieldName":"A","fieldType":{"id":19,"kind":"tup","fields":{"kind":"row","fields":[],"other":{"kind":"empty"}}}},{"fieldName":"B","fieldType":{"id":20,"kind":"int"}}],"other":{"kind":"empty"}}},"depth":0},{"id":13,"kind":"import","defName":"importedValue","protoName":"ModuleToImport"},{"id":16,"kind":"instance","protoName":"ModuleToInstantiate","overrides":[[{"id":15,"name":"C"},{"id":14,"kind":"int","value":0}]],"identityOverride":true},{"id":26,"kind":"def","name":"A","qualifier":"val","typeAnnotation":{"id":22,"kind":"const","name":"T"},"expr":{"id":25,"kind":"app","opcode":"variant","args":[{"id":23,"kind":"str","value":"A"},{"id":24,"kind":"tuple","elements":[]}]}},{"id":32,"kind":"def","name":"B","qualifier":"def","typeAnnotation":{"kind":"oper","args":[{"id":20,"kind":"int"}],"res":{"id":22,"kind":"const","name":"T"}},"expr":{"id":31,"kind":"lambda","params":[{"id":28,"name":"__BParam"}],"qualifier":"def","expr":{"id":30,"kind":"app","opcode":"variant","args":[{"id":27,"kind":"str","value":"B"},{"kind":"name","name":"__BParam","id":29}]}}},{"id":36,"kind":"def","name":"foo::bar","qualifier":"def","expr":{"id":35,"kind":"lambda","params":[{"id":33,"name":"__123"}],"qualifier":"def","expr":{"id":34,"kind":"name","name":"__123"}}},{"id":46,"kind":"def","name":"altInit","qualifier":"action","expr":{"id":45,"kind":"app","opcode":"assign","args":[{"id":44,"kind":"name","name":"x"},{"id":43,"kind":"int","value":0}]}},{"id":52,"kind":"def","name":"step","qualifier":"action","expr":{"id":51,"kind":"app","opcode":"assign","args":[{"id":50,"kind":"name","name":"x"},{"id":49,"kind":"app","opcode":"iadd","args":[{"id":47,"kind":"name","name":"x"},{"id":48,"kind":"int","value":1}]}]}},{"id":58,"kind":"def","name":"altStep","qualifier":"action","expr":{"id":57,"kind":"app","opcode":"assign","args":[{"id":56,"kind":"name","name":"x"},{"id":55,"kind":"app","opcode":"iadd","args":[{"id":53,"kind":"name","name":"x"},{"id":54,"kind":"int","value":0}]}]}},{"id":62,"kind":"def","name":"inv","qualifier":"def","expr":{"id":61,"kind":"app","opcode":"igte","args":[{"id":59,"kind":"name","name":"x"},{"id":60,"kind":"int","value":0}]}},{"id":66,"kind":"def","name":"altInv","qualifier":"def","expr":{"id":65,"kind":"app","opcode":"igte","args":[{"id":63,"kind":"name","name":"x"},{"id":64,"kind":"int","value":0}]}},{"id":42,"kind":"def","name":"init","qualifier":"action","expr":{"id":41,"kind":"app","opcode":"assign","args":[{"id":40,"kind":"name","name":"x"},{"id":39,"kind":"app","opcode":"iadd","args":[{"id":37,"kind":"name","name":"importedValue"},{"id":38,"kind":"name","name":"instantiatedValue"}]}]}}]}],"table":{"3":{"kind":"const","name":"C","typeAnnotation":{"id":1,"kind":"int"},"id":2,"depth":0},"4":{"id":4,"kind":"def","name":"instantiatedValue","qualifier":"val","expr":{"id":3,"kind":"name","name":"C"},"depth":0},"7":{"id":7,"kind":"def","name":"importedValue","qualifier":"val","expr":{"id":6,"kind":"int","value":0},"depth":0},"9":{"id":9,"kind":"def","name":"init","qualifier":"action","expr":{"id":8,"kind":"bool","value":true},"depth":0},"11":{"id":11,"kind":"def","name":"step","qualifier":"action","expr":{"id":10,"kind":"bool","value":true},"depth":0},"15":{"kind":"const","name":"C","typeAnnotation":{"id":1,"kind":"int"},"id":2,"depth":0,"importedFrom":{"id":16,"kind":"instance","protoName":"ModuleToInstantiate","overrides":[[{"id":15,"name":"C"},{"id":14,"kind":"int","value":0}]],"identityOverride":true},"hidden":true,"namespaces":["ModuleToInstantiate","ApalacheCompilation"]},"22":{"id":21,"kind":"typedef","name":"T","type":{"id":21,"kind":"sum","fields":{"kind":"row","fields":[{"fieldName":"A","fieldType":{"id":19,"kind":"tup","fields":{"kind":"row","fields":[],"other":{"kind":"empty"}}}},{"fieldName":"B","fieldType":{"id":20,"kind":"int"}}],"other":{"kind":"empty"}}},"depth":0},"26":{"id":26,"kind":"def","name":"A","qualifier":"val","typeAnnotation":{"id":22,"kind":"const","name":"T"},"expr":{"id":25,"kind":"app","opcode":"variant","args":[{"id":23,"kind":"str","value":"A"},{"id":24,"kind":"tuple","elements":[]}]},"depth":0},"29":{"id":28,"name":"__BParam","kind":"param","depth":1},"32":{"id":32,"kind":"def","name":"B","qualifier":"def","typeAnnotation":{"kind":"oper","args":[{"id":20,"kind":"int"}],"res":{"id":22,"kind":"const","name":"T"}},"expr":{"id":31,"kind":"lambda","params":[{"id":28,"name":"__BParam"}],"qualifier":"def","expr":{"id":30,"kind":"app","opcode":"variant","args":[{"id":27,"kind":"str","value":"B"},{"kind":"name","name":"__BParam","id":29}]}},"depth":0},"34":{"id":33,"name":"__123","kind":"param","depth":1},"36":{"id":36,"kind":"def","name":"foo::bar","qualifier":"def","expr":{"id":35,"kind":"lambda","params":[{"id":33,"name":"__123"}],"qualifier":"def","expr":{"id":34,"kind":"name","name":"__123"}},"depth":0},"37":{"id":7,"kind":"def","name":"importedValue","qualifier":"val","expr":{"id":6,"kind":"int","value":0},"depth":0,"importedFrom":{"id":13,"kind":"import","defName":"importedValue","protoName":"ModuleToImport"},"hidden":true},"38":{"id":4,"kind":"def","name":"instantiatedValue","qualifier":"val","expr":{"id":3,"kind":"name","name":"C"},"depth":0,"importedFrom":{"id":16,"kind":"instance","protoName":"ModuleToInstantiate","overrides":[[{"id":15,"name":"C"},{"id":14,"kind":"int","value":0}]],"identityOverride":true},"hidden":true,"namespaces":["ModuleToInstantiate","ApalacheCompilation"]},"40":{"kind":"var","name":"x","typeAnnotation":{"id":17,"kind":"int"},"id":18,"depth":0},"42":{"id":42,"kind":"def","name":"init","qualifier":"action","expr":{"id":41,"kind":"app","opcode":"assign","args":[{"id":40,"kind":"name","name":"x"},{"id":39,"kind":"app","opcode":"iadd","args":[{"id":37,"kind":"name","name":"importedValue"},{"id":38,"kind":"name","name":"instantiatedValue"}]}]},"depth":0},"44":{"kind":"var","name":"x","typeAnnotation":{"id":17,"kind":"int"},"id":18,"depth":0},"46":{"id":46,"kind":"def","name":"altInit","qualifier":"action","expr":{"id":45,"kind":"app","opcode":"assign","args":[{"id":44,"kind":"name","name":"x"},{"id":43,"kind":"int","value":0}]},"depth":0},"47":{"kind":"var","name":"x","typeAnnotation":{"id":17,"kind":"int"},"id":18,"depth":0},"50":{"kind":"var","name":"x","typeAnnotation":{"id":17,"kind":"int"},"id":18,"depth":0},"52":{"id":52,"kind":"def","name":"step","qualifier":"action","expr":{"id":51,"kind":"app","opcode":"assign","args":[{"id":50,"kind":"name","name":"x"},{"id":49,"kind":"app","opcode":"iadd","args":[{"id":47,"kind":"name","name":"x"},{"id":48,"kind":"int","value":1}]}]},"depth":0},"53":{"kind":"var","name":"x","typeAnnotation":{"id":17,"kind":"int"},"id":18,"depth":0},"56":{"kind":"var","name":"x","typeAnnotation":{"id":17,"kind":"int"},"id":18,"depth":0},"58":{"id":58,"kind":"def","name":"altStep","qualifier":"action","expr":{"id":57,"kind":"app","opcode":"assign","args":[{"id":56,"kind":"name","name":"x"},{"id":55,"kind":"app","opcode":"iadd","args":[{"id":53,"kind":"name","name":"x"},{"id":54,"kind":"int","value":0}]}]},"depth":0},"59":{"kind":"var","name":"x","typeAnnotation":{"id":17,"kind":"int"},"id":18,"depth":0},"62":{"id":62,"kind":"def","name":"inv","qualifier":"def","expr":{"id":61,"kind":"app","opcode":"igte","args":[{"id":59,"kind":"name","name":"x"},{"id":60,"kind":"int","value":0}]},"depth":0},"63":{"kind":"var","name":"x","typeAnnotation":{"id":17,"kind":"int"},"id":18,"depth":0},"66":{"id":66,"kind":"def","name":"altInv","qualifier":"def","expr":{"id":65,"kind":"app","opcode":"igte","args":[{"id":63,"kind":"name","name":"x"},{"id":64,"kind":"int","value":0}]},"depth":0}},"errors":[]}