{"sourceIndex":{"0":"mocked_path/testFixture/SuperSpec.qnt"},"map":{"1":[0,{"line":1,"col":12,"index":24},{"line":1,"col":12,"index":24}],"2":[0,{"line":1,"col":2,"index":14},{"line":1,"col":12,"index":24}],"3":[0,{"line":0,"col":0,"index":0},{"line":2,"col":26,"index":26}],"4":[0,{"line":5,"col":12,"index":53},{"line":5,"col":12,"index":53}],"5":[0,{"line":5,"col":2,"index":43},{"line":5,"col":12,"index":53}],"6":[0,{"line":4,"col":0,"index":29},{"line":6,"col":26,"index":55}],"7":[0,{"line":9,"col":11,"index":84},{"line":9,"col":13,"index":86}],"8":[0,{"line":9,"col":2,"index":75},{"line":9,"col":13,"index":86}],"9":[0,{"line":10,"col":9,"index":97},{"line":10,"col":11,"index":99}],"10":[0,{"line":10,"col":2,"index":90},{"line":10,"col":11,"index":99}],"11":[0,{"line":8,"col":0,"index":58},{"line":11,"col":43,"index":101}],"12":[0,{"line":16,"col":11,"index":186},{"line":16,"col":13,"index":188}],"13":[0,{"line":16,"col":2,"index":177},{"line":16,"col":13,"index":188}],"14":[0,{"line":17,"col":15,"index":205},{"line":17,"col":17,"index":207}],"15":[0,{"line":17,"col":11,"index":201},{"line":17,"col":18,"index":208}],"16":[0,{"line":17,"col":2,"index":192},{"line":17,"col":18,"index":208}],"17":[0,{"line":18,"col":19,"index":229},{"line":18,"col":21,"index":231}],"18":[0,{"line":18,"col":15,"index":225},{"line":18,"col":22,"index":232}],"19":[0,{"line":18,"col":2,"index":212},{"line":18,"col":22,"index":232}],"20":[0,{"line":19,"col":20,"index":254},{"line":19,"col":23,"index":257}],"21":[0,{"line":19,"col":15,"index":249},{"line":19,"col":24,"index":258}],"22":[0,{"line":19,"col":2,"index":236},{"line":19,"col":24,"index":258}],"23":[0,{"line":20,"col":15,"index":275},{"line":20,"col":17,"index":277}],"24":[0,{"line":20,"col":22,"index":282},{"line":20,"col":24,"index":284}],"25":[0,{"line":20,"col":15,"index":275},{"line":20,"col":24,"index":284}],"26":[0,{"line":20,"col":2,"index":262},{"line":20,"col":24,"index":284}],"27":[0,{"line":21,"col":19,"index":305},{"line":21,"col":21,"index":307}],"28":[0,{"line":21,"col":26,"index":312},{"line":21,"col":28,"index":314}],"29":[0,{"line":21,"col":19,"index":305},{"line":21,"col":28,"index":314}],"30":[0,{"line":21,"col":34,"index":320},{"line":21,"col":37,"index":323}],"31":[0,{"line":21,"col":18,"index":304},{"line":21,"col":37,"index":323}],"32":[0,{"line":21,"col":2,"index":288},{"line":21,"col":37,"index":323}],"33":[0,{"line":22,"col":21,"index":346},{"line":22,"col":23,"index":348}],"34":[0,{"line":22,"col":26,"index":351},{"line":22,"col":28,"index":353}],"35":[0,{"line":22,"col":34,"index":359},{"line":22,"col":37,"index":362}],"36":[0,{"line":22,"col":20,"index":345},{"line":22,"col":37,"index":362}],"37":[0,{"line":22,"col":2,"index":327},{"line":22,"col":37,"index":362}],"38":[0,{"line":23,"col":30,"index":394},{"line":23,"col":32,"index":396}],"39":[0,{"line":23,"col":35,"index":399},{"line":23,"col":37,"index":401}],"40":[0,{"line":23,"col":45,"index":409},{"line":23,"col":48,"index":412}],"41":[0,{"line":23,"col":29,"index":393},{"line":23,"col":48,"index":412}],"42":[0,{"line":23,"col":2,"index":366},{"line":23,"col":48,"index":412}],"43":[0,{"line":24,"col":18,"index":432},{"line":24,"col":20,"index":434}],"44":[0,{"line":24,"col":23,"index":437},{"line":24,"col":26,"index":440}],"45":[0,{"line":24,"col":29,"index":443},{"line":24,"col":31,"index":445}],"46":[0,{"line":24,"col":17,"index":431},{"line":24,"col":32,"index":446}],"47":[0,{"line":24,"col":2,"index":416},{"line":24,"col":32,"index":446}],"48":[0,{"line":25,"col":27,"index":475},{"line":25,"col":29,"index":477}],"49":[0,{"line":25,"col":32,"index":480},{"line":25,"col":35,"index":483}],"50":[0,{"line":25,"col":38,"index":486},{"line":25,"col":40,"index":488}],"51":[0,{"line":25,"col":26,"index":474},{"line":25,"col":43,"index":491}],"52":[0,{"line":25,"col":2,"index":450},{"line":25,"col":43,"index":491}],"53":[0,{"line":28,"col":23,"index":580},{"line":28,"col":25,"index":582}],"54":[0,{"line":28,"col":31,"index":588},{"line":28,"col":34,"index":591}],"55":[0,{"line":28,"col":40,"index":597},{"line":28,"col":42,"index":599}],"56":[0,{"line":28,"col":18,"index":575},{"line":28,"col":44,"index":601}],"57":[0,{"line":28,"col":2,"index":559},{"line":28,"col":44,"index":601}],"58":[0,{"line":29,"col":32,"index":635},{"line":29,"col":34,"index":637}],"59":[0,{"line":29,"col":40,"index":643},{"line":29,"col":43,"index":646}],"60":[0,{"line":29,"col":49,"index":652},{"line":29,"col":51,"index":654}],"61":[0,{"line":29,"col":27,"index":630},{"line":29,"col":54,"index":657}],"62":[0,{"line":29,"col":2,"index":605},{"line":29,"col":54,"index":657}],"63":[0,{"line":32,"col":33,"index":731},{"line":32,"col":35,"index":733}],"64":[0,{"line":32,"col":2,"index":700},{"line":32,"col":35,"index":733}],"65":[0,{"line":36,"col":15,"index":822},{"line":36,"col":17,"index":824}],"66":[0,{"line":37,"col":26,"index":853},{"line":37,"col":28,"index":855}],"67":[0,{"line":37,"col":39,"index":866},{"line":37,"col":41,"index":868}],"68":[0,{"line":37,"col":18,"index":845},{"line":37,"col":43,"index":870}],"69":[0,{"line":38,"col":12,"index":885},{"line":38,"col":14,"index":887}],"70":[0,{"line":35,"col":2,"index":788},{"line":38,"col":102,"index":888}],"71":[0,{"line":35,"col":2,"index":788},{"line":38,"col":102,"index":888}],"72":[0,{"line":36,"col":8,"index":815},{"line":36,"col":18,"index":825}],"73":[0,{"line":36,"col":15,"index":822},{"line":36,"col":17,"index":824}],"74":[0,{"line":36,"col":8,"index":815},{"line":36,"col":13,"index":820}],"75":[0,{"line":36,"col":8,"index":815},{"line":36,"col":18,"index":825}],"76":[0,{"line":36,"col":8,"index":815},{"line":36,"col":18,"index":825}],"77":[0,{"line":36,"col":8,"index":815},{"line":36,"col":18,"index":825}],"78":[0,{"line":37,"col":8,"index":835},{"line":37,"col":44,"index":871}],"79":[0,{"line":37,"col":18,"index":845},{"line":37,"col":43,"index":870}],"80":[0,{"line":37,"col":8,"index":835},{"line":37,"col":16,"index":843}],"81":[0,{"line":37,"col":8,"index":835},{"line":37,"col":44,"index":871}],"82":[0,{"line":37,"col":8,"index":835},{"line":37,"col":44,"index":871}],"83":[0,{"line":37,"col":8,"index":835},{"line":37,"col":44,"index":871}],"84":[0,{"line":38,"col":8,"index":881},{"line":38,"col":15,"index":888}],"85":[0,{"line":38,"col":12,"index":885},{"line":38,"col":14,"index":887}],"86":[0,{"line":38,"col":8,"index":881},{"line":38,"col":10,"index":883}],"87":[0,{"line":38,"col":8,"index":881},{"line":38,"col":15,"index":888}],"88":[0,{"line":38,"col":8,"index":881},{"line":38,"col":15,"index":888}],"89":[0,{"line":38,"col":8,"index":881},{"line":38,"col":15,"index":888}],"90":[0,{"line":39,"col":17,"index":907},{"line":39,"col":27,"index":917}],"91":[0,{"line":39,"col":2,"index":892},{"line":39,"col":27,"index":917}],"92":[0,{"line":44,"col":9,"index":1031},{"line":44,"col":11,"index":1033}],"93":[0,{"line":44,"col":2,"index":1024},{"line":44,"col":11,"index":1033}],"94":[0,{"line":45,"col":9,"index":1044},{"line":45,"col":12,"index":1047}],"95":[0,{"line":45,"col":2,"index":1037},{"line":45,"col":12,"index":1047}],"96":[0,{"line":50,"col":19,"index":1216},{"line":50,"col":19,"index":1216}],"97":[0,{"line":50,"col":23,"index":1220},{"line":50,"col":23,"index":1220}],"98":[0,{"line":50,"col":19,"index":1216},{"line":50,"col":23,"index":1220}],"99":[0,{"line":50,"col":2,"index":1199},{"line":50,"col":23,"index":1220}],"100":[0,{"line":51,"col":19,"index":1241},{"line":51,"col":19,"index":1241}],"101":[0,{"line":51,"col":23,"index":1245},{"line":51,"col":23,"index":1245}],"102":[0,{"line":51,"col":19,"index":1241},{"line":51,"col":23,"index":1245}],"103":[0,{"line":51,"col":2,"index":1224},{"line":51,"col":23,"index":1245}],"104":[0,{"line":52,"col":19,"index":1266},{"line":52,"col":19,"index":1266}],"105":[0,{"line":52,"col":23,"index":1270},{"line":52,"col":23,"index":1270}],"106":[0,{"line":52,"col":19,"index":1266},{"line":52,"col":23,"index":1270}],"107":[0,{"line":52,"col":2,"index":1249},{"line":52,"col":23,"index":1270}],"108":[0,{"line":53,"col":19,"index":1291},{"line":53,"col":19,"index":1291}],"109":[0,{"line":53,"col":23,"index":1295},{"line":53,"col":23,"index":1295}],"110":[0,{"line":53,"col":19,"index":1291},{"line":53,"col":23,"index":1295}],"111":[0,{"line":53,"col":2,"index":1274},{"line":53,"col":23,"index":1295}],"112":[0,{"line":54,"col":19,"index":1316},{"line":54,"col":19,"index":1316}],"113":[0,{"line":54,"col":23,"index":1320},{"line":54,"col":23,"index":1320}],"114":[0,{"line":54,"col":19,"index":1316},{"line":54,"col":23,"index":1320}],"115":[0,{"line":54,"col":2,"index":1299},{"line":54,"col":23,"index":1320}],"116":[0,{"line":55,"col":19,"index":1341},{"line":55,"col":19,"index":1341}],"117":[0,{"line":55,"col":21,"index":1343},{"line":55,"col":21,"index":1343}],"118":[0,{"line":55,"col":19,"index":1341},{"line":55,"col":21,"index":1343}],"119":[0,{"line":55,"col":2,"index":1324},{"line":55,"col":21,"index":1343}],"120":[0,{"line":56,"col":16,"index":1361},{"line":56,"col":18,"index":1363}],"121":[0,{"line":56,"col":15,"index":1360},{"line":56,"col":18,"index":1363}],"122":[0,{"line":56,"col":2,"index":1347},{"line":56,"col":18,"index":1363}],"123":[0,{"line":57,"col":18,"index":1383},{"line":57,"col":18,"index":1383}],"124":[0,{"line":57,"col":22,"index":1387},{"line":57,"col":22,"index":1387}],"125":[0,{"line":57,"col":18,"index":1383},{"line":57,"col":22,"index":1387}],"126":[0,{"line":57,"col":2,"index":1367},{"line":57,"col":22,"index":1387}],"127":[0,{"line":58,"col":18,"index":1407},{"line":58,"col":18,"index":1407}],"128":[0,{"line":58,"col":23,"index":1412},{"line":58,"col":23,"index":1412}],"129":[0,{"line":58,"col":18,"index":1407},{"line":58,"col":23,"index":1412}],"130":[0,{"line":58,"col":2,"index":1391},{"line":58,"col":23,"index":1412}],"131":[0,{"line":59,"col":18,"index":1432},{"line":59,"col":18,"index":1432}],"132":[0,{"line":59,"col":22,"index":1436},{"line":59,"col":22,"index":1436}],"133":[0,{"line":59,"col":18,"index":1432},{"line":59,"col":22,"index":1436}],"134":[0,{"line":59,"col":2,"index":1416},{"line":59,"col":22,"index":1436}],"135":[0,{"line":60,"col":18,"index":1456},{"line":60,"col":18,"index":1456}],"136":[0,{"line":60,"col":23,"index":1461},{"line":60,"col":23,"index":1461}],"137":[0,{"line":60,"col":18,"index":1456},{"line":60,"col":23,"index":1461}],"138":[0,{"line":60,"col":2,"index":1440},{"line":60,"col":23,"index":1461}],"139":[0,{"line":61,"col":20,"index":1483},{"line":61,"col":20,"index":1483}],"140":[0,{"line":61,"col":25,"index":1488},{"line":61,"col":25,"index":1488}],"141":[0,{"line":61,"col":20,"index":1483},{"line":61,"col":25,"index":1488}],"142":[0,{"line":61,"col":2,"index":1465},{"line":61,"col":25,"index":1488}],"143":[0,{"line":62,"col":18,"index":1508},{"line":62,"col":18,"index":1508}],"144":[0,{"line":62,"col":23,"index":1513},{"line":62,"col":23,"index":1513}],"145":[0,{"line":62,"col":18,"index":1508},{"line":62,"col":23,"index":1513}],"146":[0,{"line":62,"col":2,"index":1492},{"line":62,"col":23,"index":1513}],"147":[0,{"line":64,"col":6,"index":1540},{"line":64,"col":6,"index":1540}],"148":[0,{"line":64,"col":10,"index":1544},{"line":64,"col":10,"index":1544}],"149":[0,{"line":64,"col":6,"index":1540},{"line":64,"col":10,"index":1544}],"150":[0,{"line":64,"col":15,"index":1549},{"line":64,"col":15,"index":1549}],"151":[0,{"line":64,"col":6,"index":1540},{"line":64,"col":15,"index":1549}],"152":[0,{"line":63,"col":2,"index":1517},{"line":65,"col":38,"index":1553}],"153":[0,{"line":66,"col":25,"index":1580},{"line":66,"col":25,"index":1580}],"154":[0,{"line":66,"col":30,"index":1585},{"line":66,"col":32,"index":1587}],"155":[0,{"line":66,"col":25,"index":1580},{"line":66,"col":33,"index":1588}],"156":[0,{"line":66,"col":2,"index":1557},{"line":66,"col":33,"index":1588}],"157":[0,{"line":67,"col":23,"index":1613},{"line":67,"col":26,"index":1616}],"158":[0,{"line":67,"col":35,"index":1625},{"line":67,"col":35,"index":1625}],"159":[0,{"line":67,"col":40,"index":1630},{"line":67,"col":40,"index":1630}],"160":[0,{"line":67,"col":35,"index":1625},{"line":67,"col":40,"index":1630}],"161":[0,{"line":67,"col":23,"index":1613},{"line":67,"col":41,"index":1631}],"162":[0,{"line":67,"col":2,"index":1592},{"line":67,"col":41,"index":1631}],"163":[0,{"line":70,"col":20,"index":1670},{"line":70,"col":22,"index":1672}],"164":[0,{"line":70,"col":16,"index":1666},{"line":70,"col":23,"index":1673}],"165":[0,{"line":70,"col":31,"index":1681},{"line":70,"col":31,"index":1681}],"166":[0,{"line":70,"col":34,"index":1684},{"line":70,"col":34,"index":1684}],"167":[0,{"line":70,"col":27,"index":1677},{"line":70,"col":35,"index":1685}],"168":[0,{"line":70,"col":2,"index":1652},{"line":70,"col":35,"index":1685}],"169":[0,{"line":72,"col":2,"index":1724},{"line":72,"col":10,"index":1732}],"170":[0,{"line":73,"col":33,"index":1767},{"line":73,"col":36,"index":1770}],"171":[0,{"line":73,"col":29,"index":1763},{"line":73,"col":37,"index":1771}],"172":[0,{"line":73,"col":41,"index":1775},{"line":73,"col":45,"index":1779}],"173":[0,{"line":73,"col":2,"index":1736},{"line":73,"col":45,"index":1779}],"174":[0,{"line":76,"col":9,"index":1817},{"line":76,"col":11,"index":1819}],"175":[0,{"line":76,"col":2,"index":1810},{"line":76,"col":11,"index":1819}],"176":[0,{"line":77,"col":25,"index":1846},{"line":77,"col":26,"index":1847}],"177":[0,{"line":77,"col":2,"index":1823},{"line":77,"col":26,"index":1847}],"178":[0,{"line":78,"col":15,"index":1864},{"line":78,"col":15,"index":1864}],"179":[0,{"line":78,"col":18,"index":1867},{"line":78,"col":18,"index":1867}],"180":[0,{"line":78,"col":23,"index":1872},{"line":78,"col":23,"index":1872}],"181":[0,{"line":78,"col":27,"index":1876},{"line":78,"col":27,"index":1876}],"182":[0,{"line":78,"col":23,"index":1872},{"line":78,"col":27,"index":1876}],"183":[0,{"line":78,"col":2,"index":1851},{"line":78,"col":27,"index":1876}],"184":[0,{"line":78,"col":2,"index":1851},{"line":78,"col":27,"index":1876}],"185":[0,{"line":79,"col":10,"index":1888},{"line":79,"col":15,"index":1893}],"186":[0,{"line":79,"col":20,"index":1898},{"line":79,"col":25,"index":1903}],"187":[0,{"line":79,"col":29,"index":1907},{"line":79,"col":29,"index":1907}],"188":[0,{"line":79,"col":20,"index":1898},{"line":79,"col":29,"index":1907}],"189":[0,{"line":79,"col":2,"index":1880},{"line":79,"col":29,"index":1907}],"190":[0,{"line":79,"col":2,"index":1880},{"line":79,"col":29,"index":1907}],"191":[0,{"line":80,"col":11,"index":1920},{"line":80,"col":11,"index":1920}],"192":[0,{"line":80,"col":21,"index":1930},{"line":80,"col":21,"index":1930}],"193":[0,{"line":80,"col":16,"index":1925},{"line":80,"col":21,"index":1930}],"194":[0,{"line":80,"col":16,"index":1925},{"line":80,"col":21,"index":1930}],"195":[0,{"line":80,"col":2,"index":1911},{"line":80,"col":21,"index":1930}],"196":[0,{"line":80,"col":2,"index":1911},{"line":80,"col":21,"index":1930}],"197":[0,{"line":81,"col":13,"index":1945},{"line":81,"col":13,"index":1945}],"198":[0,{"line":81,"col":22,"index":1954},{"line":81,"col":22,"index":1954}],"199":[0,{"line":81,"col":18,"index":1950},{"line":81,"col":23,"index":1955}],"200":[0,{"line":81,"col":2,"index":1934},{"line":81,"col":23,"index":1955}],"201":[0,{"line":81,"col":2,"index":1934},{"line":81,"col":23,"index":1955}],"202":[0,{"line":84,"col":8,"index":1987},{"line":84,"col":8,"index":1987}],"203":[0,{"line":84,"col":11,"index":1990},{"line":84,"col":11,"index":1990}],"204":[0,{"line":84,"col":16,"index":1995},{"line":84,"col":18,"index":1997}],"205":[0,{"line":84,"col":21,"index":2000},{"line":84,"col":23,"index":2002}],"206":[0,{"line":84,"col":29,"index":2008},{"line":84,"col":31,"index":2010}],"207":[0,{"line":84,"col":15,"index":1994},{"line":84,"col":31,"index":2010}],"208":[0,{"line":85,"col":6,"index":2022},{"line":85,"col":6,"index":2022}],"209":[0,{"line":85,"col":10,"index":2026},{"line":85,"col":10,"index":2026}],"210":[0,{"line":85,"col":6,"index":2022},{"line":85,"col":10,"index":2026}],"211":[0,{"line":84,"col":2,"index":1981},{"line":86,"col":51,"index":2030}],"212":[0,{"line":84,"col":2,"index":1981},{"line":86,"col":51,"index":2030}],"213":[0,{"line":88,"col":10,"index":2073},{"line":88,"col":10,"index":2073}],"214":[0,{"line":88,"col":15,"index":2078},{"line":88,"col":15,"index":2078}],"215":[0,{"line":88,"col":21,"index":2084},{"line":88,"col":21,"index":2084}],"216":[0,{"line":88,"col":14,"index":2077},{"line":88,"col":21,"index":2084}],"217":[0,{"line":89,"col":6,"index":2096},{"line":89,"col":6,"index":2096}],"218":[0,{"line":88,"col":2,"index":2065},{"line":90,"col":37,"index":2100}],"219":[0,{"line":88,"col":2,"index":2065},{"line":90,"col":37,"index":2100}],"220":[0,{"line":92,"col":9,"index":2112},{"line":92,"col":11,"index":2114}],"221":[0,{"line":92,"col":2,"index":2105},{"line":92,"col":11,"index":2114}],"222":[0,{"line":93,"col":21,"index":2137},{"line":93,"col":21,"index":2137}],"223":[0,{"line":93,"col":16,"index":2132},{"line":93,"col":21,"index":2137}],"224":[0,{"line":93,"col":16,"index":2132},{"line":93,"col":21,"index":2137}],"225":[0,{"line":93,"col":2,"index":2118},{"line":93,"col":21,"index":2137}],"226":[0,{"line":97,"col":18,"index":2259},{"line":97,"col":20,"index":2261}],"227":[0,{"line":97,"col":15,"index":2256},{"line":97,"col":20,"index":2261}],"228":[0,{"line":97,"col":26,"index":2267},{"line":97,"col":28,"index":2269}],"229":[0,{"line":97,"col":23,"index":2264},{"line":97,"col":28,"index":2269}],"230":[0,{"line":97,"col":33,"index":2274},{"line":97,"col":35,"index":2276}],"231":[0,{"line":98,"col":8,"index":2290},{"line":98,"col":8,"index":2290}],"232":[0,{"line":98,"col":12,"index":2294},{"line":98,"col":12,"index":2294}],"233":[0,{"line":98,"col":8,"index":2290},{"line":98,"col":12,"index":2294}],"234":[0,{"line":99,"col":4,"index":2301},{"line":99,"col":4,"index":2301}],"235":[0,{"line":100,"col":9,"index":2312},{"line":100,"col":9,"index":2312}],"236":[0,{"line":98,"col":4,"index":2286},{"line":100,"col":30,"index":2312}],"237":[0,{"line":97,"col":2,"index":2243},{"line":101,"col":75,"index":2316}],"238":[0,{"line":97,"col":2,"index":2243},{"line":101,"col":75,"index":2316}],"239":[0,{"line":105,"col":17,"index":2360},{"line":105,"col":21,"index":2364}],"240":[0,{"line":105,"col":27,"index":2370},{"line":105,"col":30,"index":2373}],"241":[0,{"line":105,"col":17,"index":2360},{"line":105,"col":30,"index":2373}],"242":[0,{"line":105,"col":2,"index":2345},{"line":105,"col":30,"index":2373}],"243":[0,{"line":106,"col":16,"index":2391},{"line":106,"col":20,"index":2395}],"244":[0,{"line":106,"col":25,"index":2400},{"line":106,"col":28,"index":2403}],"245":[0,{"line":106,"col":16,"index":2391},{"line":106,"col":28,"index":2403}],"246":[0,{"line":106,"col":2,"index":2377},{"line":106,"col":28,"index":2403}],"247":[0,{"line":107,"col":21,"index":2426},{"line":107,"col":25,"index":2430}],"248":[0,{"line":107,"col":35,"index":2440},{"line":107,"col":38,"index":2443}],"249":[0,{"line":107,"col":21,"index":2426},{"line":107,"col":38,"index":2443}],"250":[0,{"line":107,"col":2,"index":2407},{"line":107,"col":38,"index":2443}],"251":[0,{"line":108,"col":8,"index":2453},{"line":108,"col":8,"index":2453}],"252":[0,{"line":108,"col":13,"index":2458},{"line":108,"col":13,"index":2458}],"253":[0,{"line":108,"col":2,"index":2447},{"line":108,"col":13,"index":2458}],"254":[0,{"line":108,"col":2,"index":2447},{"line":108,"col":13,"index":2458}],"255":[0,{"line":109,"col":8,"index":2468},{"line":109,"col":8,"index":2468}],"256":[0,{"line":109,"col":15,"index":2475},{"line":109,"col":15,"index":2475}],"257":[0,{"line":109,"col":13,"index":2473},{"line":109,"col":16,"index":2476}],"258":[0,{"line":109,"col":26,"index":2486},{"line":109,"col":26,"index":2486}],"259":[0,{"line":109,"col":22,"index":2482},{"line":109,"col":27,"index":2487}],"260":[0,{"line":109,"col":13,"index":2473},{"line":109,"col":27,"index":2487}],"261":[0,{"line":109,"col":2,"index":2462},{"line":109,"col":27,"index":2487}],"262":[0,{"line":109,"col":2,"index":2462},{"line":109,"col":27,"index":2487}],"263":[0,{"line":110,"col":19,"index":2508},{"line":110,"col":19,"index":2508}],"264":[0,{"line":110,"col":26,"index":2515},{"line":110,"col":26,"index":2515}],"265":[0,{"line":110,"col":24,"index":2513},{"line":110,"col":27,"index":2516}],"266":[0,{"line":110,"col":37,"index":2526},{"line":110,"col":37,"index":2526}],"267":[0,{"line":110,"col":33,"index":2522},{"line":110,"col":38,"index":2527}],"268":[0,{"line":110,"col":24,"index":2513},{"line":110,"col":38,"index":2527}],"269":[0,{"line":110,"col":2,"index":2491},{"line":110,"col":38,"index":2527}],"270":[0,{"line":110,"col":2,"index":2491},{"line":110,"col":38,"index":2527}],"271":[0,{"line":111,"col":18,"index":2547},{"line":111,"col":18,"index":2547}],"272":[0,{"line":111,"col":25,"index":2554},{"line":111,"col":25,"index":2554}],"273":[0,{"line":111,"col":23,"index":2552},{"line":111,"col":26,"index":2555}],"274":[0,{"line":111,"col":35,"index":2564},{"line":111,"col":35,"index":2564}],"275":[0,{"line":111,"col":31,"index":2560},{"line":111,"col":36,"index":2565}],"276":[0,{"line":111,"col":23,"index":2552},{"line":111,"col":36,"index":2565}],"277":[0,{"line":111,"col":2,"index":2531},{"line":111,"col":36,"index":2565}],"278":[0,{"line":111,"col":2,"index":2531},{"line":111,"col":36,"index":2565}],"279":[0,{"line":114,"col":6,"index":2603},{"line":114,"col":10,"index":2607}],"280":[0,{"line":115,"col":6,"index":2616},{"line":115,"col":9,"index":2619}],"281":[0,{"line":116,"col":6,"index":2628},{"line":116,"col":10,"index":2632}],"282":[0,{"line":113,"col":23,"index":2591},{"line":117,"col":68,"index":2636}],"283":[0,{"line":113,"col":2,"index":2570},{"line":117,"col":68,"index":2636}],"284":[0,{"line":120,"col":6,"index":2678},{"line":120,"col":10,"index":2682}],"285":[0,{"line":121,"col":6,"index":2691},{"line":121,"col":9,"index":2694}],"286":[0,{"line":122,"col":6,"index":2703},{"line":122,"col":10,"index":2707}],"287":[0,{"line":119,"col":27,"index":2666},{"line":123,"col":72,"index":2711}],"288":[0,{"line":119,"col":2,"index":2641},{"line":123,"col":72,"index":2711}],"289":[0,{"line":126,"col":6,"index":2747},{"line":126,"col":10,"index":2751}],"290":[0,{"line":127,"col":6,"index":2760},{"line":127,"col":9,"index":2763}],"291":[0,{"line":128,"col":6,"index":2772},{"line":128,"col":10,"index":2776}],"292":[0,{"line":125,"col":22,"index":2736},{"line":129,"col":66,"index":2780}],"293":[0,{"line":125,"col":2,"index":2716},{"line":129,"col":66,"index":2780}],"294":[0,{"line":132,"col":6,"index":2821},{"line":132,"col":10,"index":2825}],"295":[0,{"line":133,"col":6,"index":2834},{"line":133,"col":9,"index":2837}],"296":[0,{"line":134,"col":6,"index":2846},{"line":134,"col":10,"index":2850}],"297":[0,{"line":131,"col":26,"index":2809},{"line":135,"col":71,"index":2854}],"298":[0,{"line":131,"col":2,"index":2785},{"line":135,"col":71,"index":2854}],"299":[0,{"line":137,"col":21,"index":2878},{"line":137,"col":24,"index":2881}],"300":[0,{"line":137,"col":27,"index":2884},{"line":137,"col":27,"index":2884}],"301":[0,{"line":137,"col":34,"index":2891},{"line":137,"col":34,"index":2891}],"302":[0,{"line":137,"col":17,"index":2874},{"line":137,"col":34,"index":2891}],"303":[0,{"line":137,"col":2,"index":2859},{"line":137,"col":34,"index":2891}],"304":[0,{"line":138,"col":16,"index":2909},{"line":138,"col":16,"index":2909}],"305":[0,{"line":138,"col":19,"index":2912},{"line":138,"col":19,"index":2912}],"306":[0,{"line":138,"col":28,"index":2921},{"line":138,"col":28,"index":2921}],"307":[0,{"line":138,"col":32,"index":2925},{"line":138,"col":33,"index":2926}],"308":[0,{"line":138,"col":28,"index":2921},{"line":138,"col":33,"index":2926}],"309":[0,{"line":138,"col":36,"index":2929},{"line":138,"col":36,"index":2929}],"310":[0,{"line":138,"col":40,"index":2933},{"line":138,"col":40,"index":2933}],"311":[0,{"line":138,"col":36,"index":2929},{"line":138,"col":40,"index":2933}],"312":[0,{"line":138,"col":47,"index":2940},{"line":138,"col":47,"index":2940}],"313":[0,{"line":138,"col":51,"index":2944},{"line":138,"col":51,"index":2944}],"314":[0,{"line":138,"col":47,"index":2940},{"line":138,"col":51,"index":2944}],"315":[0,{"line":138,"col":24,"index":2917},{"line":138,"col":51,"index":2944}],"316":[0,{"line":138,"col":2,"index":2895},{"line":138,"col":51,"index":2944}],"317":[0,{"line":138,"col":2,"index":2895},{"line":138,"col":51,"index":2944}],"318":[0,{"line":141,"col":10,"index":2983},{"line":141,"col":12,"index":2985}],"319":[0,{"line":141,"col":17,"index":2990},{"line":141,"col":19,"index":2992}],"320":[0,{"line":141,"col":10,"index":2983},{"line":141,"col":19,"index":2992}],"321":[0,{"line":141,"col":2,"index":2975},{"line":141,"col":19,"index":2992}],"322":[0,{"line":142,"col":15,"index":3009},{"line":142,"col":16,"index":3010}],"323":[0,{"line":142,"col":22,"index":3016},{"line":142,"col":24,"index":3018}],"324":[0,{"line":142,"col":15,"index":3009},{"line":142,"col":25,"index":3019}],"325":[0,{"line":142,"col":2,"index":2996},{"line":142,"col":25,"index":3019}],"326":[0,{"line":145,"col":13,"index":3083},{"line":145,"col":13,"index":3083}],"327":[0,{"line":145,"col":16,"index":3086},{"line":145,"col":16,"index":3086}],"328":[0,{"line":145,"col":21,"index":3091},{"line":145,"col":21,"index":3091}],"329":[0,{"line":145,"col":2,"index":3072},{"line":145,"col":21,"index":3091}],"330":[0,{"line":145,"col":2,"index":3072},{"line":145,"col":21,"index":3091}],"331":[0,{"line":146,"col":31,"index":3124},{"line":146,"col":33,"index":3126}],"332":[0,{"line":146,"col":36,"index":3129},{"line":146,"col":37,"index":3130}],"333":[0,{"line":146,"col":24,"index":3117},{"line":146,"col":38,"index":3131}],"334":[0,{"line":146,"col":2,"index":3095},{"line":146,"col":38,"index":3131}],"335":[0,{"line":147,"col":22,"index":3155},{"line":147,"col":24,"index":3157}],"336":[0,{"line":147,"col":33,"index":3166},{"line":147,"col":34,"index":3167}],"337":[0,{"line":147,"col":22,"index":3155},{"line":147,"col":35,"index":3168}],"338":[0,{"line":147,"col":2,"index":3135},{"line":147,"col":35,"index":3168}],"339":[0,{"line":149,"col":19,"index":3246},{"line":149,"col":19,"index":3246}],"340":[0,{"line":149,"col":22,"index":3249},{"line":149,"col":26,"index":3253}],"341":[0,{"line":149,"col":16,"index":3243},{"line":149,"col":27,"index":3254}],"342":[0,{"line":149,"col":2,"index":3229},{"line":149,"col":27,"index":3254}],"343":[0,{"line":154,"col":22,"index":3423},{"line":154,"col":22,"index":3423}],"344":[0,{"line":154,"col":31,"index":3432},{"line":154,"col":31,"index":3432}],"345":[0,{"line":154,"col":36,"index":3437},{"line":154,"col":36,"index":3437}],"346":[0,{"line":154,"col":40,"index":3441},{"line":154,"col":41,"index":3442}],"347":[0,{"line":154,"col":36,"index":3437},{"line":154,"col":41,"index":3442}],"348":[0,{"line":154,"col":31,"index":3432},{"line":154,"col":41,"index":3442}],"349":[0,{"line":154,"col":22,"index":3423},{"line":154,"col":42,"index":3443}],"350":[0,{"line":154,"col":2,"index":3403},{"line":154,"col":42,"index":3443}],"351":[0,{"line":156,"col":25,"index":3500},{"line":156,"col":25,"index":3500}],"352":[0,{"line":156,"col":28,"index":3503},{"line":156,"col":32,"index":3507}],"353":[0,{"line":156,"col":18,"index":3493},{"line":156,"col":33,"index":3508}],"354":[0,{"line":156,"col":42,"index":3517},{"line":156,"col":42,"index":3517}],"355":[0,{"line":156,"col":45,"index":3520},{"line":156,"col":47,"index":3522}],"356":[0,{"line":156,"col":54,"index":3529},{"line":156,"col":54,"index":3529}],"357":[0,{"line":156,"col":58,"index":3533},{"line":156,"col":60,"index":3535}],"358":[0,{"line":156,"col":54,"index":3529},{"line":156,"col":60,"index":3535}],"359":[0,{"line":156,"col":40,"index":3515},{"line":156,"col":60,"index":3535}],"360":[0,{"line":156,"col":40,"index":3515},{"line":156,"col":60,"index":3535}],"361":[0,{"line":156,"col":40,"index":3515},{"line":156,"col":60,"index":3535}],"362":[0,{"line":156,"col":40,"index":3515},{"line":156,"col":60,"index":3535}],"363":[0,{"line":156,"col":40,"index":3515},{"line":156,"col":60,"index":3535}],"364":[0,{"line":156,"col":40,"index":3515},{"line":156,"col":60,"index":3535}],"365":[0,{"line":156,"col":40,"index":3515},{"line":156,"col":60,"index":3535}],"366":[0,{"line":156,"col":40,"index":3515},{"line":156,"col":60,"index":3535}],"367":[0,{"line":156,"col":40,"index":3515},{"line":156,"col":60,"index":3535}],"368":[0,{"line":156,"col":40,"index":3515},{"line":156,"col":60,"index":3535}],"369":[0,{"line":156,"col":18,"index":3493},{"line":156,"col":62,"index":3537}],"370":[0,{"line":156,"col":2,"index":3477},{"line":156,"col":62,"index":3537}],"371":[0,{"line":159,"col":21,"index":3602},{"line":159,"col":21,"index":3602}],"372":[0,{"line":159,"col":15,"index":3596},{"line":159,"col":22,"index":3603}],"373":[0,{"line":159,"col":4,"index":3585},{"line":159,"col":22,"index":3603}],"374":[0,{"line":161,"col":6,"index":3621},{"line":161,"col":6,"index":3621}],"375":[0,{"line":161,"col":10,"index":3625},{"line":161,"col":11,"index":3626}],"376":[0,{"line":161,"col":6,"index":3621},{"line":161,"col":11,"index":3626}],"377":[0,{"line":162,"col":11,"index":3640},{"line":162,"col":11,"index":3640}],"378":[0,{"line":162,"col":6,"index":3635},{"line":162,"col":11,"index":3640}],"379":[0,{"line":162,"col":6,"index":3635},{"line":162,"col":11,"index":3640}],"380":[0,{"line":160,"col":4,"index":3609},{"line":163,"col":41,"index":3646}],"381":[0,{"line":159,"col":4,"index":3585},{"line":163,"col":65,"index":3646}],"382":[0,{"line":158,"col":2,"index":3558},{"line":164,"col":94,"index":3650}],"383":[0,{"line":166,"col":22,"index":3689},{"line":166,"col":22,"index":3689}],"384":[0,{"line":166,"col":31,"index":3698},{"line":166,"col":31,"index":3698}],"385":[0,{"line":166,"col":36,"index":3703},{"line":166,"col":39,"index":3706}],"386":[0,{"line":166,"col":31,"index":3698},{"line":166,"col":39,"index":3706}],"387":[0,{"line":166,"col":22,"index":3689},{"line":166,"col":40,"index":3707}],"388":[0,{"line":166,"col":2,"index":3669},{"line":166,"col":40,"index":3707}],"389":[0,{"line":168,"col":10,"index":3720},{"line":168,"col":10,"index":3720}],"390":[0,{"line":168,"col":18,"index":3728},{"line":168,"col":18,"index":3728}],"391":[0,{"line":168,"col":23,"index":3733},{"line":168,"col":23,"index":3733}],"392":[0,{"line":168,"col":27,"index":3737},{"line":168,"col":27,"index":3737}],"393":[0,{"line":168,"col":23,"index":3733},{"line":168,"col":27,"index":3737}],"394":[0,{"line":168,"col":18,"index":3728},{"line":168,"col":27,"index":3737}],"395":[0,{"line":168,"col":10,"index":3720},{"line":168,"col":28,"index":3738}],"396":[0,{"line":168,"col":2,"index":3712},{"line":168,"col":28,"index":3738}],"397":[0,{"line":170,"col":23,"index":3764},{"line":170,"col":23,"index":3764}],"398":[0,{"line":170,"col":37,"index":3778},{"line":170,"col":37,"index":3778}],"399":[0,{"line":170,"col":40,"index":3781},{"line":170,"col":40,"index":3781}],"400":[0,{"line":170,"col":33,"index":3774},{"line":170,"col":41,"index":3782}],"401":[0,{"line":170,"col":23,"index":3764},{"line":170,"col":42,"index":3783}],"402":[0,{"line":170,"col":2,"index":3743},{"line":170,"col":42,"index":3783}],"403":[0,{"line":173,"col":17,"index":3842},{"line":173,"col":17,"index":3842}],"404":[0,{"line":173,"col":20,"index":3845},{"line":173,"col":20,"index":3845}],"405":[0,{"line":173,"col":12,"index":3837},{"line":173,"col":21,"index":3846}],"406":[0,{"line":173,"col":12,"index":3837},{"line":173,"col":28,"index":3853}],"407":[0,{"line":173,"col":2,"index":3827},{"line":173,"col":28,"index":3853}],"408":[0,{"line":176,"col":20,"index":3897},{"line":176,"col":20,"index":3897}],"409":[0,{"line":176,"col":23,"index":3900},{"line":176,"col":23,"index":3900}],"410":[0,{"line":176,"col":26,"index":3903},{"line":176,"col":26,"index":3903}],"411":[0,{"line":176,"col":19,"index":3896},{"line":176,"col":27,"index":3904}],"412":[0,{"line":176,"col":2,"index":3879},{"line":176,"col":27,"index":3904}],"413":[0,{"line":177,"col":24,"index":3930},{"line":177,"col":24,"index":3930}],"414":[0,{"line":177,"col":27,"index":3933},{"line":177,"col":27,"index":3933}],"415":[0,{"line":177,"col":30,"index":3936},{"line":177,"col":30,"index":3936}],"416":[0,{"line":177,"col":20,"index":3926},{"line":177,"col":31,"index":3937}],"417":[0,{"line":177,"col":2,"index":3908},{"line":177,"col":31,"index":3937}],"418":[0,{"line":178,"col":18,"index":3957},{"line":178,"col":18,"index":3957}],"419":[0,{"line":178,"col":23,"index":3962},{"line":178,"col":23,"index":3962}],"420":[0,{"line":178,"col":18,"index":3957},{"line":178,"col":23,"index":3962}],"421":[0,{"line":178,"col":2,"index":3941},{"line":178,"col":23,"index":3962}],"422":[0,{"line":179,"col":19,"index":3983},{"line":179,"col":19,"index":3983}],"423":[0,{"line":179,"col":22,"index":3986},{"line":179,"col":22,"index":3986}],"424":[0,{"line":179,"col":25,"index":3989},{"line":179,"col":25,"index":3989}],"425":[0,{"line":179,"col":18,"index":3982},{"line":179,"col":26,"index":3990}],"426":[0,{"line":179,"col":2,"index":3966},{"line":179,"col":26,"index":3990}],"427":[0,{"line":180,"col":24,"index":4016},{"line":180,"col":24,"index":4016}],"428":[0,{"line":180,"col":27,"index":4019},{"line":180,"col":27,"index":4019}],"429":[0,{"line":180,"col":30,"index":4022},{"line":180,"col":30,"index":4022}],"430":[0,{"line":180,"col":19,"index":4011},{"line":180,"col":31,"index":4023}],"431":[0,{"line":180,"col":2,"index":3994},{"line":180,"col":31,"index":4023}],"432":[0,{"line":181,"col":23,"index":4048},{"line":181,"col":23,"index":4048}],"433":[0,{"line":181,"col":26,"index":4051},{"line":181,"col":26,"index":4051}],"434":[0,{"line":181,"col":29,"index":4054},{"line":181,"col":29,"index":4054}],"435":[0,{"line":181,"col":22,"index":4047},{"line":181,"col":30,"index":4055}],"436":[0,{"line":181,"col":32,"index":4057},{"line":181,"col":32,"index":4057}],"437":[0,{"line":181,"col":22,"index":4047},{"line":181,"col":33,"index":4058}],"438":[0,{"line":181,"col":2,"index":4027},{"line":181,"col":33,"index":4058}],"439":[0,{"line":182,"col":28,"index":4088},{"line":182,"col":33,"index":4093}],"440":[0,{"line":182,"col":22,"index":4082},{"line":182,"col":33,"index":4093}],"441":[0,{"line":182,"col":42,"index":4102},{"line":182,"col":45,"index":4105}],"442":[0,{"line":182,"col":36,"index":4096},{"line":182,"col":45,"index":4105}],"443":[0,{"line":182,"col":20,"index":4080},{"line":182,"col":47,"index":4107}],"444":[0,{"line":182,"col":2,"index":4062},{"line":182,"col":47,"index":4107}],"445":[0,{"line":183,"col":25,"index":4134},{"line":183,"col":30,"index":4139}],"446":[0,{"line":183,"col":33,"index":4142},{"line":183,"col":38,"index":4147}],"447":[0,{"line":183,"col":41,"index":4150},{"line":183,"col":46,"index":4155}],"448":[0,{"line":183,"col":49,"index":4158},{"line":183,"col":52,"index":4161}],"449":[0,{"line":183,"col":21,"index":4130},{"line":183,"col":53,"index":4162}],"450":[0,{"line":183,"col":2,"index":4111},{"line":183,"col":53,"index":4162}],"451":[0,{"line":184,"col":29,"index":4193},{"line":184,"col":35,"index":4199}],"452":[0,{"line":184,"col":23,"index":4187},{"line":184,"col":35,"index":4199}],"453":[0,{"line":184,"col":44,"index":4208},{"line":184,"col":47,"index":4211}],"454":[0,{"line":184,"col":38,"index":4202},{"line":184,"col":47,"index":4211}],"455":[0,{"line":184,"col":53,"index":4217},{"line":184,"col":63,"index":4227}],"456":[0,{"line":184,"col":21,"index":4185},{"line":184,"col":65,"index":4229}],"457":[0,{"line":184,"col":21,"index":4185},{"line":184,"col":65,"index":4229}],"458":[0,{"line":184,"col":2,"index":4166},{"line":184,"col":65,"index":4229}],"459":[0,{"line":185,"col":21,"index":4252},{"line":185,"col":21,"index":4252}],"460":[0,{"line":185,"col":24,"index":4255},{"line":185,"col":24,"index":4255}],"461":[0,{"line":185,"col":27,"index":4258},{"line":185,"col":27,"index":4258}],"462":[0,{"line":185,"col":17,"index":4248},{"line":185,"col":28,"index":4259}],"463":[0,{"line":185,"col":2,"index":4233},{"line":185,"col":28,"index":4259}],"464":[0,{"line":189,"col":22,"index":4331},{"line":189,"col":22,"index":4331}],"465":[0,{"line":189,"col":19,"index":4328},{"line":189,"col":22,"index":4331}],"466":[0,{"line":189,"col":28,"index":4337},{"line":189,"col":32,"index":4341}],"467":[0,{"line":189,"col":25,"index":4334},{"line":189,"col":32,"index":4341}],"468":[0,{"line":189,"col":17,"index":4326},{"line":189,"col":34,"index":4343}],"469":[0,{"line":189,"col":4,"index":4313},{"line":189,"col":34,"index":4343}],"470":[0,{"line":190,"col":4,"index":4349},{"line":190,"col":9,"index":4354}],"471":[0,{"line":190,"col":4,"index":4349},{"line":190,"col":11,"index":4356}],"472":[0,{"line":190,"col":4,"index":4349},{"line":190,"col":11,"index":4356}],"473":[0,{"line":189,"col":4,"index":4313},{"line":190,"col":47,"index":4356}],"474":[0,{"line":188,"col":2,"index":4293},{"line":190,"col":65,"index":4356}],"475":[0,{"line":193,"col":21,"index":4397},{"line":193,"col":23,"index":4399}],"476":[0,{"line":193,"col":26,"index":4402},{"line":193,"col":26,"index":4402}],"477":[0,{"line":193,"col":17,"index":4393},{"line":193,"col":27,"index":4403}],"478":[0,{"line":193,"col":4,"index":4380},{"line":193,"col":27,"index":4403}],"479":[0,{"line":194,"col":4,"index":4409},{"line":194,"col":9,"index":4414}],"480":[0,{"line":194,"col":4,"index":4409},{"line":194,"col":12,"index":4417}],"481":[0,{"line":194,"col":4,"index":4409},{"line":194,"col":12,"index":4417}],"482":[0,{"line":193,"col":4,"index":4380},{"line":194,"col":41,"index":4417}],"483":[0,{"line":192,"col":2,"index":4361},{"line":194,"col":58,"index":4417}],"484":[0,{"line":196,"col":14,"index":4434},{"line":196,"col":14,"index":4434}],"485":[0,{"line":196,"col":19,"index":4439},{"line":196,"col":19,"index":4439}],"486":[0,{"line":196,"col":24,"index":4444},{"line":196,"col":25,"index":4445}],"487":[0,{"line":196,"col":19,"index":4439},{"line":196,"col":25,"index":4445}],"488":[0,{"line":196,"col":2,"index":4422},{"line":196,"col":25,"index":4445}],"489":[0,{"line":196,"col":2,"index":4422},{"line":196,"col":25,"index":4445}],"490":[0,{"line":199,"col":19,"index":4493},{"line":199,"col":19,"index":4493}],"491":[0,{"line":199,"col":24,"index":4498},{"line":199,"col":28,"index":4502}],"492":[0,{"line":199,"col":19,"index":4493},{"line":199,"col":29,"index":4503}],"493":[0,{"line":199,"col":2,"index":4476},{"line":199,"col":29,"index":4503}],"494":[0,{"line":200,"col":23,"index":4528},{"line":200,"col":27,"index":4532}],"495":[0,{"line":200,"col":38,"index":4543},{"line":200,"col":42,"index":4547}],"496":[0,{"line":200,"col":23,"index":4528},{"line":200,"col":43,"index":4548}],"497":[0,{"line":200,"col":2,"index":4507},{"line":200,"col":43,"index":4548}],"498":[0,{"line":201,"col":22,"index":4572},{"line":201,"col":22,"index":4572}],"499":[0,{"line":201,"col":18,"index":4568},{"line":201,"col":23,"index":4573}],"500":[0,{"line":201,"col":41,"index":4591},{"line":201,"col":41,"index":4591}],"501":[0,{"line":201,"col":43,"index":4593},{"line":201,"col":43,"index":4593}],"502":[0,{"line":201,"col":45,"index":4595},{"line":201,"col":45,"index":4595}],"503":[0,{"line":201,"col":37,"index":4587},{"line":201,"col":46,"index":4596}],"504":[0,{"line":201,"col":28,"index":4578},{"line":201,"col":47,"index":4597}],"505":[0,{"line":201,"col":18,"index":4568},{"line":201,"col":48,"index":4598}],"506":[0,{"line":201,"col":2,"index":4552},{"line":201,"col":48,"index":4598}],"507":[0,{"line":204,"col":18,"index":4648},{"line":204,"col":18,"index":4648}],"508":[0,{"line":204,"col":21,"index":4651},{"line":204,"col":21,"index":4651}],"509":[0,{"line":204,"col":14,"index":4644},{"line":204,"col":22,"index":4652}],"510":[0,{"line":204,"col":37,"index":4667},{"line":204,"col":37,"index":4667}],"511":[0,{"line":204,"col":14,"index":4644},{"line":204,"col":38,"index":4668}],"512":[0,{"line":204,"col":2,"index":4632},{"line":204,"col":38,"index":4668}],"513":[0,{"line":207,"col":20,"index":4715},{"line":207,"col":20,"index":4715}],"514":[0,{"line":207,"col":24,"index":4719},{"line":207,"col":24,"index":4719}],"515":[0,{"line":207,"col":20,"index":4715},{"line":207,"col":24,"index":4719}],"516":[0,{"line":207,"col":2,"index":4697},{"line":207,"col":24,"index":4719}],"517":[0,{"line":209,"col":13,"index":4763},{"line":209,"col":13,"index":4763}],"518":[0,{"line":209,"col":18,"index":4768},{"line":209,"col":18,"index":4768}],"519":[0,{"line":209,"col":13,"index":4763},{"line":209,"col":18,"index":4768}],"520":[0,{"line":209,"col":2,"index":4752},{"line":209,"col":18,"index":4768}],"521":[0,{"line":212,"col":2,"index":4786},{"line":212,"col":14,"index":4798}],"522":[0,{"line":213,"col":2,"index":4802},{"line":213,"col":12,"index":4812}],"523":[0,{"line":216,"col":21,"index":4850},{"line":216,"col":23,"index":4852}],"524":[0,{"line":216,"col":17,"index":4846},{"line":216,"col":24,"index":4853}],"525":[0,{"line":216,"col":2,"index":4831},{"line":216,"col":24,"index":4853}],"526":[0,{"line":218,"col":2,"index":4858},{"line":218,"col":24,"index":4880}],"527":[0,{"line":220,"col":10,"index":4893},{"line":220,"col":16,"index":4899}],"528":[0,{"line":220,"col":2,"index":4885},{"line":220,"col":16,"index":4899}],"529":[0,{"line":229,"col":19,"index":5187},{"line":229,"col":19,"index":5187}],"530":[0,{"line":229,"col":15,"index":5183},{"line":229,"col":15,"index":5183}],"531":[0,{"line":229,"col":2,"index":5170},{"line":229,"col":30,"index":5198}],"532":[0,{"line":14,"col":0,"index":140},{"line":233,"col":5137,"index":5277}]}}