{"stage":"parsing","warnings":[],"modules":[{"id":3,"name":"M1","defs":[{"id":2,"kind":"def","name":"foo","qualifier":"val","expr":{"id":1,"kind":"int","value":4}}]},{"id":6,"name":"M2","defs":[{"id":5,"kind":"def","name":"bar","qualifier":"val","expr":{"id":4,"kind":"int","value":4}}]},{"id":11,"name":"Proto","defs":[{"kind":"const","name":"N","typeAnnotation":{"id":7,"kind":"int"},"id":8},{"kind":"var","name":"x","typeAnnotation":{"id":9,"kind":"int"},"id":10}]},{"id":503,"name":"withConsts","defs":[{"kind":"const","name":"N","typeAnnotation":{"id":12,"kind":"int"},"id":13},{"kind":"const","name":"S","typeAnnotation":{"id":15,"kind":"set","elem":{"id":14,"kind":"int"}},"id":16},{"kind":"const","name":"MySet","typeAnnotation":{"id":18,"kind":"set","elem":{"id":17,"kind":"int"}},"id":19},{"kind":"const","name":"MySeq","typeAnnotation":{"id":21,"kind":"list","elem":{"id":20,"kind":"bool"}},"id":22},{"kind":"const","name":"MyFun","typeAnnotation":{"id":25,"kind":"fun","arg":{"id":23,"kind":"int"},"res":{"id":24,"kind":"str"}},"id":26},{"kind":"const","name":"MyFunFun","typeAnnotation":{"id":31,"kind":"fun","arg":{"id":29,"kind":"fun","arg":{"id":27,"kind":"int"},"res":{"id":28,"kind":"str"}},"res":{"id":30,"kind":"bool"}},"id":32},{"kind":"const","name":"MyOperator","typeAnnotation":{"id":36,"kind":"oper","args":[{"id":33,"kind":"int"},{"id":34,"kind":"str"}],"res":{"id":35,"kind":"bool"}},"id":37},{"kind":"const","name":"MyOperatorWithComma","typeAnnotation":{"id":41,"kind":"oper","args":[{"id":38,"kind":"int"},{"id":39,"kind":"str"}],"res":{"id":40,"kind":"bool"}},"id":42},{"kind":"const","name":"MyTuple","typeAnnotation":{"id":46,"kind":"tup","fields":{"kind":"row","fields":[{"fieldName":"0","fieldType":{"id":43,"kind":"int"}},{"fieldName":"1","fieldType":{"id":44,"kind":"bool"}},{"fieldName":"2","fieldType":{"id":45,"kind":"str"}}],"other":{"kind":"empty"}}},"id":47},{"kind":"const","name":"MyTupleWithComma","typeAnnotation":{"id":51,"kind":"tup","fields":{"kind":"row","fields":[{"fieldName":"0","fieldType":{"id":48,"kind":"int"}},{"fieldName":"1","fieldType":{"id":49,"kind":"bool"}},{"fieldName":"2","fieldType":{"id":50,"kind":"str"}}],"other":{"kind":"empty"}}},"id":52},{"kind":"const","name":"MyRecord","typeAnnotation":{"id":56,"kind":"rec","fields":{"kind":"row","fields":[{"fieldName":"i","fieldType":{"id":53,"kind":"int"}},{"fieldName":"b","fieldType":{"id":54,"kind":"bool"}},{"fieldName":"s","fieldType":{"id":55,"kind":"str"}}],"other":{"kind":"empty"}}},"id":57},{"kind":"const","name":"MyRecordWithComma","typeAnnotation":{"id":61,"kind":"rec","fields":{"kind":"row","fields":[{"fieldName":"i","fieldType":{"id":58,"kind":"int"}},{"fieldName":"b","fieldType":{"id":59,"kind":"bool"}},{"fieldName":"s","fieldType":{"id":60,"kind":"str"}}],"other":{"kind":"empty"}}},"id":62},{"kind":"const","name":"MyUnion","typeAnnotation":{"id":67,"kind":"union","tag":"tag","records":[{"tagValue":"circle","fields":{"kind":"row","fields":[{"fieldName":"radius","fieldType":{"id":63,"kind":"int"}}],"other":{"kind":"empty"}}},{"tagValue":"rectangle","fields":{"kind":"row","fields":[{"fieldName":"width","fieldType":{"id":64,"kind":"int"}},{"fieldName":"height","fieldType":{"id":65,"kind":"int"}}],"other":{"kind":"empty"}}},{"tagValue":"dog","fields":{"kind":"row","fields":[{"fieldName":"name","fieldType":{"id":66,"kind":"str"}}],"other":{"kind":"empty"}}}]},"id":68},{"kind":"const","name":"MyUnionWithComma","typeAnnotation":{"id":73,"kind":"union","tag":"tag","records":[{"tagValue":"circle","fields":{"kind":"row","fields":[{"fieldName":"radius","fieldType":{"id":69,"kind":"int"}}],"other":{"kind":"empty"}}},{"tagValue":"rectangle","fields":{"kind":"row","fields":[{"fieldName":"width","fieldType":{"id":70,"kind":"int"}},{"fieldName":"height","fieldType":{"id":71,"kind":"int"}}],"other":{"kind":"empty"}}},{"tagValue":"dog","fields":{"kind":"row","fields":[{"fieldName":"name","fieldType":{"id":72,"kind":"str"}}],"other":{"kind":"empty"}}}]},"id":74},{"kind":"var","name":"i","typeAnnotation":{"id":75,"kind":"int"},"id":76},{"kind":"var","name":"j","typeAnnotation":{"id":77,"kind":"bool"},"id":78},{"id":82,"kind":"def","name":"add_1_to_2","qualifier":"val","expr":{"id":81,"kind":"app","opcode":"iadd","args":[{"id":79,"kind":"int","value":1},{"id":80,"kind":"int","value":2}]}},{"id":86,"kind":"def","name":"sub_1_to_2","qualifier":"val","expr":{"id":85,"kind":"app","opcode":"isub","args":[{"id":83,"kind":"int","value":1},{"id":84,"kind":"int","value":2}]}},{"id":90,"kind":"def","name":"mul_2_to_3","qualifier":"val","expr":{"id":89,"kind":"app","opcode":"imul","args":[{"id":87,"kind":"int","value":2},{"id":88,"kind":"int","value":3}]}},{"id":94,"kind":"def","name":"div_2_to_3","qualifier":"val","expr":{"id":93,"kind":"app","opcode":"idiv","args":[{"id":91,"kind":"int","value":2},{"id":92,"kind":"int","value":3}]}},{"id":98,"kind":"def","name":"mod_2_to_3","qualifier":"val","expr":{"id":97,"kind":"app","opcode":"imod","args":[{"id":95,"kind":"int","value":2},{"id":96,"kind":"int","value":3}]}},{"id":102,"kind":"def","name":"pow_2_to_3","qualifier":"val","expr":{"id":101,"kind":"app","opcode":"ipow","args":[{"id":99,"kind":"int","value":2},{"id":100,"kind":"int","value":3}]}},{"id":105,"kind":"def","name":"uminus","qualifier":"val","expr":{"id":104,"kind":"app","opcode":"iuminus","args":[{"id":103,"kind":"int","value":100}]}},{"id":109,"kind":"def","name":"gt_2_to_3","qualifier":"val","expr":{"id":108,"kind":"app","opcode":"igt","args":[{"id":106,"kind":"int","value":2},{"id":107,"kind":"int","value":3}]}},{"id":113,"kind":"def","name":"ge_2_to_3","qualifier":"val","expr":{"id":112,"kind":"app","opcode":"igte","args":[{"id":110,"kind":"int","value":2},{"id":111,"kind":"int","value":3}]}},{"id":117,"kind":"def","name":"lt_2_to_3","qualifier":"val","expr":{"id":116,"kind":"app","opcode":"ilt","args":[{"id":114,"kind":"int","value":2},{"id":115,"kind":"int","value":3}]}},{"id":121,"kind":"def","name":"le_2_to_3","qualifier":"val","expr":{"id":120,"kind":"app","opcode":"ilte","args":[{"id":118,"kind":"int","value":2},{"id":119,"kind":"int","value":3}]}},{"id":125,"kind":"def","name":"eqeq_2_to_3","qualifier":"val","expr":{"id":124,"kind":"app","opcode":"eq","args":[{"id":122,"kind":"int","value":2},{"id":123,"kind":"int","value":3}]}},{"id":129,"kind":"def","name":"ne_2_to_3","qualifier":"val","expr":{"id":128,"kind":"app","opcode":"neq","args":[{"id":126,"kind":"int","value":2},{"id":127,"kind":"int","value":3}]}},{"id":135,"kind":"def","name":"VeryTrue","qualifier":"val","expr":{"id":134,"kind":"app","opcode":"eq","args":[{"id":132,"kind":"app","opcode":"iadd","args":[{"id":130,"kind":"int","value":2},{"id":131,"kind":"int","value":2}]},{"id":133,"kind":"int","value":4}]}},{"id":139,"kind":"def","name":"nat_includes_one","qualifier":"val","expr":{"id":138,"kind":"app","opcode":"in","args":[{"id":136,"kind":"int","value":1},{"id":137,"kind":"name","name":"Nat"}]}},{"id":145,"kind":"def","name":"there_is_truth","qualifier":"val","expr":{"id":144,"kind":"app","opcode":"exists","args":[{"id":140,"kind":"name","name":"Bool"},{"id":143,"kind":"lambda","params":[{"id":141,"name":"x"}],"qualifier":"def","expr":{"id":142,"kind":"name","name":"x"}}]}},{"id":151,"kind":"def","name":"withType","qualifier":"val","expr":{"id":150,"kind":"app","opcode":"Set","args":[{"id":148,"kind":"int","value":1},{"id":149,"kind":"int","value":2}]},"typeAnnotation":{"id":147,"kind":"set","elem":{"id":146,"kind":"int"}}},{"id":152,"kind":"typedef","name":"PROC"},{"id":156,"kind":"def","name":"withUninterpretedType","qualifier":"val","expr":{"id":155,"kind":"app","opcode":"Set","args":[]},"typeAnnotation":{"id":154,"kind":"set","elem":{"id":153,"kind":"const","name":"PROC"}}},{"kind":"var","name":"n","typeAnnotation":{"id":157,"kind":"int"},"id":158},{"id":160,"kind":"def","name":"magicNumber","qualifier":"pureval","expr":{"id":159,"kind":"int","value":42}},{"id":166,"kind":"def","name":"add","qualifier":"puredef","expr":{"id":166,"kind":"lambda","params":[{"id":161,"name":"x"},{"id":162,"name":"y"}],"qualifier":"puredef","expr":{"id":165,"kind":"app","opcode":"iadd","args":[{"id":163,"kind":"name","name":"x"},{"id":164,"kind":"name","name":"y"}]}}},{"id":171,"kind":"def","name":"ofN","qualifier":"def","expr":{"id":171,"kind":"lambda","params":[{"id":167,"name":"factor"}],"qualifier":"def","expr":{"id":170,"kind":"app","opcode":"imul","args":[{"id":168,"kind":"name","name":"factor"},{"id":169,"kind":"name","name":"n"}]}}},{"id":176,"kind":"def","name":"A","qualifier":"action","expr":{"id":176,"kind":"lambda","params":[{"id":172,"name":"x"}],"qualifier":"action","expr":{"id":175,"kind":"app","opcode":"assign","args":[{"id":174,"kind":"name","name":"n"},{"id":173,"kind":"name","name":"x"}]}}},{"id":180,"kind":"def","name":"B","qualifier":"puredef","expr":{"id":180,"kind":"lambda","params":[{"id":177,"name":"x"}],"qualifier":"puredef","expr":{"id":179,"kind":"app","opcode":"not","args":[{"id":178,"kind":"name","name":"x"}]}}},{"id":190,"kind":"def","name":"H","qualifier":"def","expr":{"id":190,"kind":"lambda","params":[{"id":181,"name":"x"},{"id":182,"name":"y"}],"qualifier":"def","expr":{"id":189,"kind":"app","opcode":"iadd","args":[{"id":187,"kind":"name","name":"x"},{"id":188,"kind":"name","name":"y"}]}},"typeAnnotation":{"id":186,"kind":"oper","args":[{"id":183,"kind":"int"},{"id":184,"kind":"int"}],"res":{"id":185,"kind":"int"}}},{"id":196,"kind":"def","name":"Pol","qualifier":"def","expr":{"id":196,"kind":"lambda","params":[{"id":191,"name":"x"}],"qualifier":"def","expr":{"id":195,"kind":"name","name":"x"}},"typeAnnotation":{"id":194,"kind":"oper","args":[{"id":192,"kind":"var","name":"a"}],"res":{"id":193,"kind":"var","name":"a"}}},{"kind":"var","name":"k","typeAnnotation":{"id":197,"kind":"int"},"id":198},{"id":202,"kind":"def","name":"asgn","qualifier":"action","expr":{"id":201,"kind":"app","opcode":"assign","args":[{"id":200,"kind":"name","name":"k"},{"id":199,"kind":"int","value":3}]}},{"id":215,"kind":"def","name":"min","qualifier":"puredef","expr":{"id":215,"kind":"lambda","params":[{"id":203,"name":"x"},{"id":205,"name":"y"}],"qualifier":"puredef","expr":{"id":213,"kind":"app","opcode":"ite","args":[{"id":210,"kind":"app","opcode":"ilt","args":[{"id":208,"kind":"name","name":"x"},{"id":209,"kind":"name","name":"y"}]},{"id":211,"kind":"name","name":"x"},{"id":212,"kind":"name","name":"y"}]}},"typeAnnotation":{"id":214,"kind":"oper","args":[{"id":204,"kind":"int"},{"id":206,"kind":"int"}],"res":{"id":207,"kind":"int"}}},{"id":219,"kind":"def","name":"test_and","qualifier":"val","expr":{"id":218,"kind":"app","opcode":"and","args":[{"id":216,"kind":"bool","value":false},{"id":217,"kind":"bool","value":true}]}},{"id":223,"kind":"def","name":"test_or","qualifier":"val","expr":{"id":222,"kind":"app","opcode":"or","args":[{"id":220,"kind":"bool","value":false},{"id":221,"kind":"bool","value":true}]}},{"id":227,"kind":"def","name":"test_implies","qualifier":"val","expr":{"id":226,"kind":"app","opcode":"implies","args":[{"id":224,"kind":"bool","value":false},{"id":225,"kind":"bool","value":true}]}},{"id":230,"kind":"def","name":"F","qualifier":"def","expr":{"id":230,"kind":"lambda","params":[{"id":228,"name":"x"}],"qualifier":"def","expr":{"id":229,"kind":"name","name":"x"}}},{"id":237,"kind":"def","name":"G","qualifier":"val","expr":{"id":237,"kind":"lambda","params":[{"id":231,"name":"x"}],"qualifier":"val","expr":{"id":236,"kind":"app","opcode":"and","args":[{"id":233,"kind":"app","opcode":"F","args":[{"id":232,"kind":"name","name":"x"}]},{"id":235,"kind":"app","opcode":"not","args":[{"id":234,"kind":"name","name":"x"}]}]}}},{"id":244,"kind":"def","name":"test_and_arg","qualifier":"val","expr":{"id":244,"kind":"lambda","params":[{"id":238,"name":"x"}],"qualifier":"val","expr":{"id":243,"kind":"app","opcode":"and","args":[{"id":240,"kind":"app","opcode":"F","args":[{"id":239,"kind":"name","name":"x"}]},{"id":242,"kind":"app","opcode":"not","args":[{"id":241,"kind":"name","name":"x"}]}]}}},{"id":251,"kind":"def","name":"test_or_arg","qualifier":"val","expr":{"id":251,"kind":"lambda","params":[{"id":245,"name":"x"}],"qualifier":"val","expr":{"id":250,"kind":"app","opcode":"or","args":[{"id":247,"kind":"app","opcode":"F","args":[{"id":246,"kind":"name","name":"x"}]},{"id":249,"kind":"app","opcode":"not","args":[{"id":248,"kind":"name","name":"x"}]}]}}},{"id":256,"kind":"def","name":"test_block_and","qualifier":"val","expr":{"id":255,"kind":"app","opcode":"and","args":[{"id":252,"kind":"bool","value":false},{"id":253,"kind":"bool","value":true},{"id":254,"kind":"bool","value":false}]}},{"id":261,"kind":"def","name":"test_action_and","qualifier":"action","expr":{"id":260,"kind":"app","opcode":"actionAll","args":[{"id":257,"kind":"bool","value":false},{"id":258,"kind":"bool","value":true},{"id":259,"kind":"bool","value":false}]}},{"id":266,"kind":"def","name":"test_block_or","qualifier":"val","expr":{"id":265,"kind":"app","opcode":"or","args":[{"id":262,"kind":"bool","value":false},{"id":263,"kind":"bool","value":true},{"id":264,"kind":"bool","value":false}]}},{"id":271,"kind":"def","name":"test_action_or","qualifier":"action","expr":{"id":270,"kind":"app","opcode":"actionAny","args":[{"id":267,"kind":"bool","value":false},{"id":268,"kind":"bool","value":true},{"id":269,"kind":"bool","value":false}]}},{"id":276,"kind":"def","name":"test_ite","qualifier":"val","expr":{"id":275,"kind":"app","opcode":"ite","args":[{"id":272,"kind":"bool","value":true},{"id":273,"kind":"int","value":1},{"id":274,"kind":"int","value":0}]}},{"id":289,"kind":"def","name":"test_ite2","qualifier":"def","expr":{"id":289,"kind":"lambda","params":[{"id":277,"name":"x"},{"id":278,"name":"y"}],"qualifier":"def","expr":{"id":288,"kind":"app","opcode":"ite","args":[{"id":281,"kind":"app","opcode":"ilt","args":[{"id":279,"kind":"name","name":"x"},{"id":280,"kind":"int","value":10}]},{"id":284,"kind":"app","opcode":"iadd","args":[{"id":282,"kind":"name","name":"y"},{"id":283,"kind":"int","value":5}]},{"id":287,"kind":"app","opcode":"imod","args":[{"id":285,"kind":"name","name":"y"},{"id":286,"kind":"int","value":5}]}]}}},{"kind":"var","name":"f1","typeAnnotation":{"id":292,"kind":"fun","arg":{"id":290,"kind":"str"},"res":{"id":291,"kind":"int"}},"id":293},{"id":297,"kind":"def","name":"funapp","qualifier":"val","expr":{"id":296,"kind":"app","opcode":"get","args":[{"id":294,"kind":"name","name":"f1"},{"id":295,"kind":"str","value":"a"}]}},{"id":301,"kind":"def","name":"MyOper","qualifier":"def","expr":{"id":301,"kind":"lambda","params":[{"id":298,"name":"a"},{"id":299,"name":"b"}],"qualifier":"def","expr":{"id":300,"kind":"int","value":1}}},{"id":305,"kind":"def","name":"oper_app_normal","qualifier":"val","expr":{"id":304,"kind":"app","opcode":"MyOper","args":[{"id":302,"kind":"str","value":"a"},{"id":303,"kind":"int","value":42}]}},{"id":309,"kind":"def","name":"oper_app_ufcs","qualifier":"val","expr":{"id":308,"kind":"app","opcode":"MyOper","args":[{"id":306,"kind":"str","value":"a"},{"id":307,"kind":"int","value":42}]}},{"id":313,"kind":"def","name":"oper_in","qualifier":"val","expr":{"id":312,"kind":"app","opcode":"in","args":[{"id":310,"kind":"int","value":1},{"id":311,"kind":"app","opcode":"Set","args":[]}]}},{"id":321,"kind":"def","name":"oper_app_dot1","qualifier":"val","expr":{"id":320,"kind":"app","opcode":"filter","args":[{"id":314,"kind":"name","name":"S"},{"id":319,"kind":"lambda","params":[{"id":315,"name":"x"}],"qualifier":"def","expr":{"id":318,"kind":"app","opcode":"igt","args":[{"id":316,"kind":"name","name":"x"},{"id":317,"kind":"int","value":10}]}}]}},{"id":333,"kind":"def","name":"oper_nondet","qualifier":"action","expr":{"id":331,"kind":"let","opdef":{"id":332,"kind":"def","name":"x","qualifier":"nondet","expr":{"id":323,"kind":"app","opcode":"oneOf","args":[{"id":322,"kind":"name","name":"S"}]}},"expr":{"id":330,"kind":"app","opcode":"actionAll","args":[{"id":326,"kind":"app","opcode":"igt","args":[{"id":324,"kind":"name","name":"x"},{"id":325,"kind":"int","value":10}]},{"id":329,"kind":"app","opcode":"assign","args":[{"id":328,"kind":"name","name":"k"},{"id":327,"kind":"name","name":"x"}]}]}}},{"id":339,"kind":"def","name":"oper_app_dot4","qualifier":"val","expr":{"id":338,"kind":"app","opcode":"filter","args":[{"id":334,"kind":"name","name":"S"},{"id":337,"kind":"lambda","params":[{"id":335,"name":"_"}],"qualifier":"def","expr":{"id":336,"kind":"bool","value":true}}]}},{"id":347,"kind":"def","name":"f","qualifier":"val","expr":{"id":346,"kind":"app","opcode":"mapBy","args":[{"id":340,"kind":"name","name":"S"},{"id":345,"kind":"lambda","params":[{"id":341,"name":"x"}],"qualifier":"def","expr":{"id":344,"kind":"app","opcode":"iadd","args":[{"id":342,"kind":"name","name":"x"},{"id":343,"kind":"int","value":1}]}}]}},{"id":353,"kind":"def","name":"set_difference","qualifier":"val","expr":{"id":352,"kind":"app","opcode":"exclude","args":[{"id":348,"kind":"name","name":"S"},{"id":351,"kind":"app","opcode":"Set","args":[{"id":349,"kind":"int","value":3},{"id":350,"kind":"int","value":4}]}]}},{"id":358,"kind":"def","name":"one","qualifier":"val","expr":{"id":357,"kind":"app","opcode":"head","args":[{"id":356,"kind":"app","opcode":"List","args":[{"id":354,"kind":"int","value":1},{"id":355,"kind":"int","value":2}]}]}},{"id":363,"kind":"def","name":"test_tuple","qualifier":"val","expr":{"id":362,"kind":"app","opcode":"Tup","args":[{"id":359,"kind":"int","value":1},{"id":360,"kind":"int","value":2},{"id":361,"kind":"int","value":3}]}},{"id":368,"kind":"def","name":"test_tuple2","qualifier":"val","expr":{"id":367,"kind":"app","opcode":"Tup","args":[{"id":364,"kind":"int","value":1},{"id":365,"kind":"int","value":2},{"id":366,"kind":"int","value":3}]}},{"id":372,"kind":"def","name":"test_pair","qualifier":"val","expr":{"id":371,"kind":"app","opcode":"Tup","args":[{"id":369,"kind":"int","value":4},{"id":370,"kind":"int","value":5}]}},{"id":377,"kind":"def","name":"test_list","qualifier":"val","expr":{"id":376,"kind":"app","opcode":"List","args":[{"id":373,"kind":"int","value":1},{"id":374,"kind":"int","value":2},{"id":375,"kind":"int","value":3}]}},{"id":382,"kind":"def","name":"test_list2","qualifier":"val","expr":{"id":381,"kind":"app","opcode":"List","args":[{"id":378,"kind":"int","value":1},{"id":379,"kind":"int","value":2},{"id":380,"kind":"int","value":3}]}},{"id":389,"kind":"def","name":"test_list_nth","qualifier":"val","expr":{"id":388,"kind":"app","opcode":"nth","args":[{"id":386,"kind":"app","opcode":"List","args":[{"id":383,"kind":"int","value":2},{"id":384,"kind":"int","value":3},{"id":385,"kind":"int","value":4}]},{"id":387,"kind":"int","value":2}]}},{"id":395,"kind":"def","name":"test_record","qualifier":"val","expr":{"id":394,"kind":"app","opcode":"Rec","args":[{"id":391,"kind":"str","value":"name"},{"id":390,"kind":"str","value":"igor"},{"id":393,"kind":"str","value":"year"},{"id":392,"kind":"int","value":1981}]}},{"id":401,"kind":"def","name":"test_record2","qualifier":"val","expr":{"id":400,"kind":"app","opcode":"Rec","args":[{"id":396,"kind":"str","value":"name"},{"id":397,"kind":"str","value":"igor"},{"id":398,"kind":"str","value":"year"},{"id":399,"kind":"int","value":1981}]}},{"id":409,"kind":"def","name":"test_record3","qualifier":"val","expr":{"id":408,"kind":"app","opcode":"with","args":[{"id":407,"kind":"app","opcode":"with","args":[{"id":406,"kind":"name","name":"test_record"},{"id":403,"kind":"str","value":"name"},{"id":402,"kind":"str","value":"quint"}]},{"id":405,"kind":"str","value":"year"},{"id":404,"kind":"int","value":2023}]}},{"id":414,"kind":"def","name":"test_set","qualifier":"val","expr":{"id":413,"kind":"app","opcode":"Set","args":[{"id":410,"kind":"int","value":1},{"id":411,"kind":"int","value":2},{"id":412,"kind":"int","value":3}]}},{"id":425,"kind":"def","name":"rec_field","qualifier":"val","expr":{"id":424,"kind":"let","opdef":{"id":420,"kind":"def","name":"my_rec","qualifier":"val","expr":{"id":419,"kind":"app","opcode":"Rec","args":[{"id":416,"kind":"str","value":"a"},{"id":415,"kind":"int","value":1},{"id":418,"kind":"str","value":"b"},{"id":417,"kind":"str","value":"foo"}]}},"expr":{"id":423,"kind":"app","opcode":"field","args":[{"id":421,"kind":"name","name":"my_rec"},{"id":422,"kind":"str","value":"a"}]}}},{"id":434,"kind":"def","name":"tup_elem","qualifier":"val","expr":{"id":433,"kind":"let","opdef":{"id":429,"kind":"def","name":"my_tup","qualifier":"val","expr":{"id":428,"kind":"app","opcode":"Tup","args":[{"id":426,"kind":"str","value":"a"},{"id":427,"kind":"int","value":3}]}},"expr":{"id":432,"kind":"app","opcode":"item","args":[{"id":430,"kind":"name","name":"my_tup"},{"id":431,"kind":"int","value":2}]}}},{"id":439,"kind":"def","name":"isEmpty","qualifier":"def","expr":{"id":439,"kind":"lambda","params":[{"id":435,"name":"s"}],"qualifier":"def","expr":{"id":438,"kind":"app","opcode":"eq","args":[{"id":436,"kind":"name","name":"s"},{"id":437,"kind":"app","opcode":"List","args":[]}]}}},{"id":443,"kind":"def","name":"in_2_empty","qualifier":"val","expr":{"id":442,"kind":"app","opcode":"in","args":[{"id":440,"kind":"int","value":2},{"id":441,"kind":"app","opcode":"Set","args":[]}]}},{"id":447,"kind":"def","name":"subseteq_empty","qualifier":"val","expr":{"id":446,"kind":"app","opcode":"subseteq","args":[{"id":444,"kind":"app","opcode":"Set","args":[]},{"id":445,"kind":"app","opcode":"Set","args":[]}]}},{"id":456,"kind":"def","name":"powersets","qualifier":"val","expr":{"id":455,"kind":"app","opcode":"in","args":[{"id":449,"kind":"app","opcode":"Set","args":[{"id":448,"kind":"int","value":1}]},{"id":454,"kind":"app","opcode":"powerset","args":[{"id":453,"kind":"app","opcode":"Set","args":[{"id":450,"kind":"int","value":1},{"id":451,"kind":"int","value":2},{"id":452,"kind":"int","value":3}]}]}]}},{"id":460,"kind":"assume","name":"positive","assumption":{"id":459,"kind":"app","opcode":"igt","args":[{"id":457,"kind":"name","name":"N"},{"id":458,"kind":"int","value":0}]}},{"id":464,"kind":"assume","name":"_","assumption":{"id":463,"kind":"app","opcode":"neq","args":[{"id":461,"kind":"name","name":"N"},{"id":462,"kind":"int","value":0}]}},{"id":465,"kind":"import","defName":"foo","protoName":"M1"},{"id":466,"kind":"import","defName":"*","protoName":"M2"},{"id":469,"kind":"typedef","name":"INT_SET","type":{"id":468,"kind":"set","elem":{"id":467,"kind":"int"}}},{"id":470,"kind":"typedef","name":"UNINTERPRETED_TYPE"},{"kind":"var","name":"S1","typeAnnotation":{"id":471,"kind":"const","name":"INT_SET"},"id":472},{"id":475,"kind":"instance","qualifiedName":"Inst1","protoName":"Proto","overrides":[[{"id":474,"name":"N"},{"id":473,"kind":"name","name":"N"}]],"identityOverride":false},{"id":482,"kind":"typedef","name":"ENTRY_TYPE","type":{"id":481,"kind":"union","tag":"tag","records":[{"tagValue":"Cat","fields":{"kind":"row","fields":[{"fieldName":"name","fieldType":{"id":476,"kind":"str"}},{"fieldName":"year","fieldType":{"id":477,"kind":"int"}}],"other":{"kind":"empty"}}},{"tagValue":"Date","fields":{"kind":"row","fields":[{"fieldName":"day","fieldType":{"id":478,"kind":"int"}},{"fieldName":"month","fieldType":{"id":479,"kind":"int"}},{"fieldName":"year","fieldType":{"id":480,"kind":"int"}}],"other":{"kind":"empty"}}}]}},{"id":502,"kind":"def","name":"isValid","qualifier":"def","expr":{"id":502,"kind":"lambda","params":[{"id":483,"name":"entry"}],"qualifier":"def","expr":{"id":501,"kind":"app","opcode":"unionMatch","args":[{"id":484,"kind":"name","name":"entry"},{"id":497,"kind":"str","value":"Cat"},{"id":498,"kind":"lambda","params":[{"id":485,"name":"cat"}],"qualifier":"def","expr":{"id":490,"kind":"app","opcode":"neq","args":[{"id":488,"kind":"app","opcode":"field","args":[{"id":486,"kind":"name","name":"cat"},{"id":487,"kind":"str","value":"name"}]},{"id":489,"kind":"str","value":""}]}},{"id":499,"kind":"str","value":"Date"},{"id":500,"kind":"lambda","params":[{"id":491,"name":"date"}],"qualifier":"def","expr":{"id":496,"kind":"app","opcode":"igt","args":[{"id":494,"kind":"app","opcode":"field","args":[{"id":492,"kind":"name","name":"date"},{"id":493,"kind":"str","value":"year"}]},{"id":495,"kind":"int","value":0}]}}]}}}]}],"table":{"142":{"kind":"param","reference":141},"153":{"kind":"type","reference":152},"163":{"kind":"param","reference":161},"164":{"kind":"param","reference":162},"168":{"kind":"param","reference":167},"169":{"kind":"var","reference":158,"typeAnnotation":{"id":157,"kind":"int"}},"173":{"kind":"param","reference":172},"174":{"kind":"var","reference":158,"typeAnnotation":{"id":157,"kind":"int"}},"178":{"kind":"param","reference":177},"187":{"kind":"param","reference":181},"188":{"kind":"param","reference":182},"195":{"kind":"param","reference":191},"200":{"kind":"var","reference":198,"typeAnnotation":{"id":197,"kind":"int"}},"208":{"kind":"param","reference":203},"209":{"kind":"param","reference":205},"211":{"kind":"param","reference":203},"212":{"kind":"param","reference":205},"229":{"kind":"param","reference":228},"232":{"kind":"param","reference":231},"233":{"kind":"def","reference":230},"234":{"kind":"param","reference":231},"239":{"kind":"param","reference":238},"240":{"kind":"def","reference":230},"241":{"kind":"param","reference":238},"246":{"kind":"param","reference":245},"247":{"kind":"def","reference":230},"248":{"kind":"param","reference":245},"279":{"kind":"param","reference":277},"282":{"kind":"param","reference":278},"285":{"kind":"param","reference":278},"294":{"kind":"var","reference":293,"typeAnnotation":{"id":292,"kind":"fun","arg":{"id":290,"kind":"str"},"res":{"id":291,"kind":"int"}}},"304":{"kind":"def","reference":301},"308":{"kind":"def","reference":301},"314":{"kind":"const","reference":16,"typeAnnotation":{"id":15,"kind":"set","elem":{"id":14,"kind":"int"}}},"316":{"kind":"param","reference":315},"322":{"kind":"const","reference":16,"typeAnnotation":{"id":15,"kind":"set","elem":{"id":14,"kind":"int"}}},"324":{"kind":"def","reference":332},"327":{"kind":"def","reference":332},"328":{"kind":"var","reference":198,"typeAnnotation":{"id":197,"kind":"int"}},"334":{"kind":"const","reference":16,"typeAnnotation":{"id":15,"kind":"set","elem":{"id":14,"kind":"int"}}},"340":{"kind":"const","reference":16,"typeAnnotation":{"id":15,"kind":"set","elem":{"id":14,"kind":"int"}}},"342":{"kind":"param","reference":341},"348":{"kind":"const","reference":16,"typeAnnotation":{"id":15,"kind":"set","elem":{"id":14,"kind":"int"}}},"406":{"kind":"def","reference":395},"421":{"kind":"def","reference":420},"430":{"kind":"def","reference":429},"436":{"kind":"param","reference":435},"457":{"kind":"const","reference":13,"typeAnnotation":{"id":12,"kind":"int"}},"461":{"kind":"const","reference":13,"typeAnnotation":{"id":12,"kind":"int"}},"471":{"kind":"type","reference":469,"typeAnnotation":{"id":468,"kind":"set","elem":{"id":467,"kind":"int"}}},"473":{"kind":"const","reference":13,"typeAnnotation":{"id":12,"kind":"int"}},"474":{"kind":"const","reference":473,"typeAnnotation":{"id":7,"kind":"int"}},"484":{"kind":"param","reference":483},"486":{"kind":"param","reference":485},"492":{"kind":"param","reference":491}}}